Workbook
Name \0: #REF!
Name \0: #REF!
Name \a: #N/A
Name \A: '[1]OPE-D.Guanhães'!#REF!
Name \b: #REF!
Name \c: #REF!
Name \d: #N/A
Name \e: #N/A
Name \f: #N/A
Name \F: '[1]OPE-D.Guanhães'!#REF!
Name \G: #REF!
Name \G: '[1]OPE-D.Guanhães'!#REF!
Name \h: #N/A
Name \i: #N/A
Name \j: #N/A
Name \L: #REF!
Name \m: #REF!
Name \n: #N/A
Name \O: #REF!
Name \P: #REF!
Name \P: '[1]OPE-D.Guanhães'!#REF!
Name \q: #REF!
Name \Q: '[1]OPE-D.Guanhães'!#REF!
Name \R: #REF!
Name \R: '[1]OPE-D.Guanhães'!#REF!
Name \s: #REF!
Name \SDFADFDAF: #REF!
Name \sdsds: #REF!
Name \T: #REF!
Name \V: #REF!
Name \w: #REF!
Name \x: #REF!
Name \y: #REF!
Name \z: #REF!
Name _\0: #REF!
Name _\1: #REF!
Name _\A: #REF!
Name _\b: #N/A
Name _\C: #REF!
Name _\c: #REF!
Name _\c: [3]PLMUSEU!#REF!
Name _\d: #N/A
Name _\e: #N/A
Name _\F: #N/A
Name _\G: #REF!
Name _\g: #N/A
Name _\h: #N/A
Name _\I: #REF!
Name _\i: #N/A
Name _\j: #N/A
Name _\L: #REF!
Name _\m: #N/A
Name _\n: #N/A
Name _\O: #REF!
Name _\p: #REF!
Name _\P: #REF!
Name _\q: #REF!
Name _\Q: '[1]OPE-D.Guanhães'!#REF!
Name _\R: #N/A
Name _\S: [4]COMPOS1!#REF!

Sheet F. Rosto
F1: CLASSIFICAÇÃO USO INTERNO | J1: PROJETO PRÁTICO TUBARÃO S1995-F4
A3: TÍTULO | J3: Nº VALE | N3: PÁGINA
A4: PROJETO DETALHADO | J4: PQ-8001PZ-G-11007 | N4: 1/2
A5: USINAS 1 E 2 - VALE - MOAGEM E FILTRAGEM
J6: Nº (SIGLA DA CONTRATADA) | N6: REV.
A7: PROJETO PRÁTICO TUBARÃO
A8: DESMONTAGEM E DESMOBILIZAÇÃO DE ATIVOS
A9: PLANILHA DE QUANTIDADES
N10: 7
A12: REVISÕES
A13: TE: TIPO | C13: A - PRELIMINAR | F13: C - PARA CONHECIMENTO | I13: E - PARA CONSTRUÇÃO | L13: G - CONFORME CONSTRUÍDO
A14: EMISSÃO | C14: B - PARA APROVAÇÃO | F14: D - PARA COTAÇÃO | I14: F - CONFORME COMPRADO | L14: H - CANCELADO
A15: Rev. | B15: TE | C15: Descrição | J15: Por | K15: Ver. | L15: Apr. | M15: Aut. | N15: Data
A16: 0 | B16: D | C16: PARA COTAÇÃO | J16: WSS | K16: FVC | L16: ABA | M16: RGS | N16: 45889
A17: 1 | B17: D | C17: PARA COTAÇÃO | J17: WSS | K17: FVC | L17: ABA | M17: RGS | N17: 45912
A18: 2 | B18: D | C18: REVISÃO CONFORME INDICADO | J18: WSS | K18: FVC | L18: ABA | M18: RGS | N18: 45924
A19: 3 | B19: D | C19: REVISÃO CONFORME INDICADO | J19: WSS | K19: GAP | L19: CMC | M19: RSC | N19: 45940
A20: 4 | B20: D | C20: Retirada da linha Destinação final de material SUCATA METÁLICA | J20: WSS | K20: GAP | L20: CMC | M20: RSC | N20: 45940
A21: 5 | B21: D | C21: REVISADO O ITEM 3.3.1.1.1. | J21: WSS | K21: GAP | L21: CMC | M21: RSC | N21: 45966
A22: 6 | B22: D | C22: REVISÃO DO DESCRITIVO DOS ITENS 3.2.1.1.1 E RETIRADA DO ITEM 3.2.1.1.2 | J22: WSS | K22: GV | L22: FVC | M22: RSC | N22: 46038
A23: 7 | B23: D | C23: INCLUSÃO ITEM DE ADMINISTRAÇÃO LOCAL | J23: GVV | K23: WSS | L23: WSS | M23: WSS | N23: 0/.02/26

Sheet CMS
C4: CMS C.05.05.001 | D4: =C4=E4 -> TRUE | E4: CMS C.05.05.001
C5: CMS C.05.15.005 | D5: =C5=E5 -> TRUE | E5: CMS C.05.15.005
C6: CMS C.05.15.006 | D6: =C6=E6 -> TRUE | E6: CMS C.05.15.006
C7: CMS C.05.20.001 | D7: =C7=E7 -> TRUE | E7: CMS C.05.20.001
C8: CMS C.10.25.015 | D8: =C8=E8 -> TRUE | E8: CMS C.10.25.015
C9: CMS C.10.25.020 | D9: =C9=E9 -> TRUE | E9: CMS C.10.25.020
C10: CMS C.10.25.025 | D10: =C10=E10 -> TRUE | E10: CMS C.10.25.025
C11: CMS C.10.25.030 | D11: =C11=E11 -> TRUE | E11: CMS C.10.25.030
C12: CMS C.65.15.000 | D12: =C12=E12 -> TRUE | E12: CMS C.65.15.000
C13: CMS C.70.21.000 | D13: =C13=E13 -> TRUE | E13: CMS C.70.21.000
C14: CMS D.10.20.000 | D14: =C14=E14 -> TRUE | E14: CMS D.10.20.000
C15: CMS D.10.20.010 | D15: =C15=E15 -> TRUE | E15: CMS D.10.20.010
... C30: CMS M.75.10.001 | D30: =C30=E30 -> TRUE | E30: CMS M.75.10.001

Sheet MC  Serv. Extraordinários
B2: SERVIÇOS COMPLEMENTARES DIVERSOS COM A UTILIZAÇÃO DE MÃO DE OBRA E EQUIPAMENTOS | C2: Preço Unitário Hora Normal | D2: Preço Unitário Hora Extra I | E2: Preço Unitário Hora Extra II | F2: Preço Unitário Hora Ad. Noturno
B3: SERVIÇOS COMPLEMENTARES DIVERSOS COM A UTILIZAÇÃO DE MÃO-DE-OBRA DIRETA | D3: *SABADOS | E3: *DOMINGOS/FERIADOS | F3: *SEM HORA EXTRA - APENAS NOTURNO
B4: ELETRICISTA MONTADOR | C4: 80.66112 | D4: 161.32224 | E4: 201.6528 | F4: 104.85946
B5: AJUDANTE ELETRICISTA | C5: 51.424708 | D5: 102.84942 | E5: 128.56177 | F5: 66.852121
B6: POLIVALENTE | C6: 58.63054 | D6: 117.26108 | E6: 146.57635 | F6: 76.219703
B7: AUXILIAR DE OBRAS | C7: 40.172829 | D7: 80.345658 | E7: 100.43207 | F7: 52.224678
B8: CALDEIREIRO | C8: 79.584148 | D8: 159.1683 | E8: 198.96037 | F8: 103.45939
B9: SOLDADOR TIG | C9: 94.141863 | D9: 188.28373 | E9: 235.35466 | F9: 122.38442
B10: ELETRICISTA F/C | C10: 101.78127 | D10: 203.56253 | E10: 254.45317 | F10: 132.31565
B11: MECÂNICO MONTADOR | C11: 70.417604 | D11: 140.83521 | E11: 176.04401 | F11: 91.542886
B12: MECÂNICO MONTADOR/LUBRIFICADOR | C12: 97.093944 | D12: 194.18789 | E12: 242.73486 | F12: 126.22213
B13: AJUDANTE DE MONTAGEM | C13: 40.703277 | D13: 81.406554 | E13: 101.75819 | F13: 52.91426
B14: SINALEIRO | C14: 46.603959 | D14: 93.207919 | E14: 116.5099 | F14: 60.585147
B15: MONTADOR ANDAIME | C15: 66.324283 | D15: 132.64857 | E15: 165.81071 | F15: 86.221568
... B22: JATISTA | C22: 59.783143 | D22: 119.56629 | E22: 149.45786 | F22: 77.718087
B23: MOTORISTA DE CAMINHÃO | C23: 55.239153
B24: SERVIÇOS COMPLEMENTARES DIVERSOS COM A UTILIZAÇÃO DE EQUIPAMENTOS - INCLUSO OPERADOR
B25: Guindaste 30t | C25: 353.09366 | D25: 706.18733 | E25: 882.73416 | F25: 459.02176
B26: Escavadeira com implemento sucateira | C26: 670.7287 | D26: 1341.4574 | E26: 1676.8217 | F26: 871.94731
B27: Carreta 12m | C27: 408.28807 | D27: 816.57614 | E27: 1020.7202 | F27: 530.77449
B28: Caminhão munck | C28: 283.1911 | D28: 566.3822 | E28: 707.97776 | F28: 368.14843
B29: Guindaste 160t | C29: 2234.3636 | D29: 4468.7273 | E29: 5585.9091 | F29: 2904.6727
B30: Mini escavadeira com rompedor hidráulico | C30: 488.24385 | D30: 976.4877 | E30: 1220.6096 | F30: 634.71701
B31: Caminhão basculante | C31: 133.24472 | D31: 266.48944 | E31: 333.1118 | F31: 173.21814
B32: ÔNIBUS - Transporte Interno | C32: 112.5 | D32: 225 | E32: 281.25 | F32: 146.25
B33: Tesoura hidráulica | C33: #REF! | D33: #REF! | E33: #REF! | F33: #REF!
B34: Gerador | C34: 127.12121 | D34: 254.24242 | E34: 317.80303 | F34: 165.25758

Sheet QQP
J1: PLANILHA DE QUANTIDADES E PREÇOS | Q1: COMPLEXO DE TUBARÃO
Q3: Nº VALE | S3: PÁGINA
Q4: PQ-8001PZ-G-11007
Q5: Nº (SIGLA DA CONTRATADA) | S5: REV.
S6: ='[390]F. Rosto'!N10 -> 7
A8: ITEM | B8: EAP | D8: Nº do Ativo | E8: CÓD. ATIVIDADE | J8: DESCRIÇÃO DAS ATIVIDADES | K8: UNID. | L8: CRITÉRIO DE MEDIÇÃO | Q8: QUANT. | R8: PREÇOS (R$)
B9: Área | C9: SubÁrea | E9: K | F9: TT | G9: UU | H9: VVV | I9: WWW | L9: CMS | M9: K | N9: TT | O9: UU | P9: Seq | R9: UNITÁRIO | S9: TOTAL
A10: 1 | E10: C | F10: 00 | G10: 00 | H10: 000 | I10: 000 | J10: OBRAS CIVIS, TERRAPLENAGEM, DRENAGEM E PAVIMENTAÇÃO
A11: 1.1 | E11: C | F11: 01 | G11: 00 | H11: 000 | I11: 000 | J11: MOBILIZAÇÃO / DESMOBILIZAÇÃO
A12: 1.1.1 | E12: C | F12: 01 | G12: 05 | H12: 000 | I12: 000 | J12: INSTALAÇÕES PROVISÓRIAS DE OBRAS / INSTALAÇÕES DEFINITIVAS
A13: 1.1.1.1 | E13: C | F13: 01 | G13: 05 | H13: 005 | I13: 000 | J13: MOBILIZAÇÃO / DESMOBILIZAÇÃO DE PESSOAL E EQUIPAMENTOS
A14: 1.1.1.1.1 | E14: C | F14: 01 | G14: 05 | H14: 005 | I14: 005 | J14: Mobilização de equipe e equipamentos | K14: vb | L14: CMS | M14: C | N14: 05 | O14: 05 | P14: 001 | Q14: 1 | R14: =VLOOKUP(A14,CPU!D6:$H$1888,5,FALSE) -> 0 | S14: =ROUND(R14*Q14,2) -> 0
A15: 1.1.1.1.2 | E15: C | F15: 01 | G15: 05 | H15: 005 | I15: 010 | J15: Desmobilização de equipe e equipamentos | K15: vb | L15: CMS | M15: C | N15: 05 | O15: 20 | P15: 001 | Q15: 1 | R15: =VLOOKUP(A15,CPU!D7:$H$1888,5,FALSE) -> 268104.35 | S15: =ROUND(R15*Q15,2) -> 268104.35
A16: 1.2 | E16: C | F16: 05 | G16: 00 | H16: 000 | I16: 000 | J16: INSTALAÇÕES PRELIMINARES E PROVISÓRIAS DE OBRAS / INSTALAÇÕES PERMANENTES
A17: 1.2.1 | E17: C | F17: 05 | G17: 05 | H17: 000 | I17: 000 | J17: CANTEIRO DE OBRAS
A18: 1.2.1.1 | E18: C | F18: 05 | G18: 05 | H18: 005 | I18: 015 | J18: Construção de Canteiro Completo (Adm, Vestiários, Refeitório, Armazém, etc) | K18: vb | L18: CMS | M18: C | N18: 05 | O18: 15 | P18: 005 | Q18: 1 | R18: =VLOOKUP(A18,CPU!D12:$H$1888,5,FALSE) -> 0 | S18: =ROUND(R18*Q18,2) -> 0
A19: 1.2.1.2 | E19: C | F19: 05 | G19: 05 | H19: 005 | I19: 020 | J19: Administração e Manutenção de Canteiro | K19: vb x mês | L19: CMS | M19: C | N19: 05 | O19: 15 | P19: 006 | Q19: 12 | R19: =VLOOKUP(A19,CPU!D12:$H$1888,5,FALSE) -> 122923.33 | S19: =ROUND(R19*Q19,2) -> 1475080
A20: 1.2.1.3 | E20: C | F20: 05 | G20: 05 | H20: 005 | I20: 025 | J20: Desmobilização de Canteiro Completo (Adm, Vestiários, Refeitório, Armazém, etc) | K20: vb | L20: CMS | M20: C | N20: 05 | O20: 20 | P20: 001 | Q20: 1 | R20: =VLOOKUP(A20,CPU!D12:$H$1888,5,FALSE) -> 0 | S20: =ROUND(R20*Q20,2) -> 0
A21: 1.3 | E21: C | F21: 05 | G21: 30 | H21: 000 | I21: 000 | J21: ADMINISTRAÇÃO LOCAL
A22: 1.3.1 | E22: C | F22: 05 | G22: 30 | H22: 005 | I22: 000 | J22: ADMINISTRAÇÃO LOCAL
A23: 1.3.1.1 | E23: C | F23: 05 | G23: 30 | H23: 005 | I23: 006 | J23: Administração Local | K23: vb | L23: CMS | M23: C | N23: 50 | O23: 50 | P23: 050 | Q23: 1 | R23: =VLOOKUP(A23,CPU!D15:$H$1888,5,FALSE) -> 7847042.4 | S23: =ROUND(R23*Q23,2) -> 7847042.4
A24: 2 | E24: E | F24: 00 | G24: 00 | H24: 000 | I24: 000 | J24: ENGENHARIA E GERENCIAMENTO
A25: 2.1 | E25: E | F25: 10 | G25: 00 | H25: 000 | I25: 000 | J25: PROJETO
A26: 2.1.1 | E26: E | F26: 10 | G26: 20 | H26: 000 | I26: 000 | J26: PROJETO DETALHADO
A27: 2.1.1.1 | E27: E | F27: 10 | G27: 20 | H27: 055 | I27: 010 | J27: Serviços de documentação de obras com time lapse | K27: vbxmês | L27: CMS | M27: E | N27: 00 | O27: 00 | P27: 016 | Q27: 12 | R27: =VLOOKUP(A27,CPU!D12:$H$1888,5,FALSE) -> 44245.48 | S27: =ROUND(R27*Q27,2) -> 530945.76
A28: 2.1.1.2 | E28: E | F28: 10 | G28: 20 | H28: 055 | I28: 015 | J28: Elaboração de Projetos Detalhados, vistas, cortes etc. ex. projeto de guarda-corpo e condição insegura. | K28: A1eq. | L28: CMS | M28: E | N28: 00 | O28: 00 | P28: 015 | Q28: 195 | R28: =VLOOKUP(A28,CPU!D12:$H$1888,5,FALSE) -> 2449.86 | S28: =ROUND(R28*Q28,2) -> 477722.7
A29: 2.2 | E29: C | F29: 10 | G29: 0 | H29: 0 | I29: 0 | J29: SERVIÇOS PRELIMINARES
A30: 2.2.1 | E30: C | F30: 10 | G30: 25 | H30: 0 | I30: 0 | J30: DESMONTES, DEMOLIÇÕES E REMOÇÕES
A31: 2.2.1.1 | E31: C | F31: 10 | G31: 25 | H31: 15 | I31: 0 | J31: DEMOLIÇÕES E DESMONTAGENS
A32: 2.2.1.1.1 | E32: C | F32: 10 | G32: 25 | H32: 015 | I32: 035 | J32: Demolição de concreto armado mecanizado. | K32: t | L32: CMS | M32: C | N32: 10 | O32: 25 | P32: 015 | Q32: 1500 | R32: =VLOOKUP(A32,CPU!D12:$H$1888,5,FALSE) -> 375.32 | S32: =ROUND(R32*Q32,2) -> 562980
A33: 2.2.1.2 | J33: REMOÇÃO DE MATERIAIS PROVENIENTES DE DESMONTES, DEMOLIÇÕES E DESMONTAGENS
A34: 2.2.1.2.1 | E34: C | F34: 10 | G34: 25 | H34: 90 | I34: 005 | J34: Carga, transporte e descarga de material proveniente de demolições ou desmontes para a área do CMD - Vale. CAÇAMBAS E CAMINHÃO DA CONTRATADA | K34: t | L34: CMS | M34: C | N34: 10 | O34: 25 | P34: 020 | Q34: =Q32 -> 1500 | R34: =VLOOKUP(A34,CPU!D12:$H$1888,5,FALSE) -> 119.24 | S34: =ROUND(R34*Q34,2) -> 178860
A35: 2.2.1.2.2 | E35: C | F35: 10 | G35: 25 | H35: 90 | I35: 010 | J35: Momento extraordinário de transporte de material proveniente de demolições ou desmontes para bota-fora - DMT até 25 km. CAÇAMBAS E CAMINHÃO DA CONTRATADA | K35: t x km | L35: CMS | M35: C | N35: 10 | O35: 25 | P35: 025 | Q35: =Q32*25 -> 37500 | R35: =VLOOKUP(A35,CPU!D12:$H$1888,5,FALSE) -> 8.71 | S35: =ROUND(R35*Q35,2) -> 326625
A36: 2.2.1.2.3 | E36: C | F36: 10 | G36: 25 | H36: 90 | I36: 15 | J36: Destinação final de material de proveniente de demolição, em aterro industrial externo homologado pela Vale | K36: t | L36: CMS | M36: C | N36: 10 | O36: 25 | P36: 030 | Q36: =Q32 -> 1500 | R36: =VLOOKUP(A36,CPU!D12:$H$1888,5,FALSE) -> 71.67 | S36: =ROUND(R36*Q36,2) -> 107505
A37: 2.3 | E37: C | F37: 65 | G37: 00 | H37: 000 | I37: 000 | J37: ESTRUTURAS DE CONCRETO
A38: 2.3.1 | E38: C | F38: 65 | G38: 15 | H38: 000 | I38: 000 | J38: CONCRETOS
A39: 2.3.1.1 | E39: C | F39: 65 | G39: 15 | H39: 010 | I39: 000 | J39: CONCRETO - PREPARO, TRANSPORTE, LANÇAMENTO, ADENSAMENTO E CURA (COM FORNECIMENTO DE TODOS OS MATERIAIS)
A40: 2.3.1.1.1 | E40: C | F40: 65 | G40: 15 | H40: 010 | I40: 250 | J40: CONCRETO NÃO-BOMBEADO EM ESTRUTURA DE FUNDAÇÃO FCK = 30,0 MPa. | K40: m³ | L40: CMS | M40: C | N40: 65 | O40: 15 | P40: 000 | Q40: 20 | R40: =VLOOKUP(A40,CPU!D12:$H$1888,5,FALSE) -> 1379.89 | S40: =ROUND(R40*Q40,2) -> 27597.8
A41: 3 | E41: D | F41: 0 | G41: 95 | H41: 0 | I41: 0 | J41: DESMONTAGEM DE EQUIPAMENTOS E COMPONENTES ELETROMECÂNICOS
A42: 3.1 | E42: D | F42: 10 | G42: 0 | H42: 0 | I42: 0 | J42: DESMONTAGEM DE EQUIPAMENTOS
A43: 3.1.1 | E43: D | F43: 10 | G43: 5 | H43: 0 | I43: 0 | J43: DESMONTAGEM DE EQUIPAMENTOS MECÂNICOS
A44: 3.1.1.1 | E44: D | F44: 10 | G44: 5 | H44: 5 | I44: 5 | J44: DESMONTAGEM, CARREGAMENTO, SEGREGAÇÃO PREPARAÇÃO E TRANSPORTE ATÉ O CMD VALE DE EQUIPAMENTOS MECÂNICOS - CAÇAMBAS E CAMINHÃO DA CONTRATADA. | K44: t | L44: CMS | M44: D | N44: 10 | O44: 20 | P44: 0 | Q44: =(10.8+10+16+210+260+9)*1.1 -> 567.38 | R44: =VLOOKUP(A44,CPU!D12:$H$1888,5,FALSE) -> 6077.01 | S44: =ROUND(R44*Q44,2) -> 3447973.9
A45: 3.1.1.2 | E45: D | F45: 10 | G45: 5 | H45: 10 | I45: 10 | J45: Drenagem de óleo e graxa dos equipamentos a serem desmobilizados conforme PRO-022144 | K45: Litros | L45: CMS | M45: D | N45: 10 | O45: 20 | P45: 10 | Q45: 7000 | R45: =VLOOKUP(A45,CPU!D13:$H$1888,5,FALSE) -> 36.66 | S45: =ROUND(R45*Q45,2) -> 256620
A46: 3.2 | E46: D | F46: 75 | G46: 0 | H46: 0 | I46: 0 | J46: ESTRUTURA METÁLICA / CALDEIRARIA
A47: 3.2.1 | E47: D | F47: 75 | G47: 10 | H47: 0 | I47: 0 | J47: DESMONTAGEM DE ESTRUTURAS METÁLICAS E CALDEIRARIA
A48: 3.2.1.1 | E48: D | F48: 75 | G48: 10 | H48: 15 | I48: 0 | J48: DESMONTAGEM DE ESTRUTURAS METÁLICAS E CALDEIRARIA LEVE, MÉDIA E PESADA
A49: 3.2.1.1.1 | E49: D | F49: 75 | G49: 10 | H49: 15 | I49: 1 | J49: DESMONTAGEM E/OU CARREGAMENTO, SEGREGAÇÃO E PREPARAÇÃO DENTRO DAS CAÇAMBAS DE ESTRUTURAS METÁLICAS, CHUTES, SILOS, CHAPAS, CALHAS E TUBULAÇÕES DN 8", 12", 14", 16, METAL DE TRANSPORTADOR, PIPE-RACK, INCLINADOS OU NA HORIZONTAL E NA VERTICAL BEM COMO OS SUPORTES DESTAS TUBULAÇÕES ETC - CAÇAMBAS E CAMINHÃO DA VALE. | K49: t | L49: CMS | M49: D | N49: 50 | O49: 10 | P49: 101 | Q49: 2076.5 | R49: =VLOOKUP(A49,CPU!D17:$H$1888,5,FALSE) -> 6549.93 | S49: =ROUND(R49*Q49,2) -> 13600930
A50: 3.3 | E50: D | F50: 60 | G50: 0 | H50: 0 | I50: 0 | J50: LIMPEZA DE EQUIPAMENTOS MECÂNICOS
A51: 3.3.1 | E51: D | F51: 60 | G51: 10 | H51: 0 | I51: 0 | J51: LIMPEZA DE MATERIAIS INCRUSTADOS
A52: 3.3.1.1 | E52: D | F52: 60 | G52: 10 | H52: 5 | I52: 0 | J52: LIMPEZA DE MATERIAIS INCRUSTADOS EM EQUIPAMENTOS MECÂNICOS
A53: 3.3.1.1.1 | E53: D | F53: 90 | G53: 10 | H53: 5 | I53: 1 | J53: LIMPEZA E REMOÇÃO DE MATERIAIS EM EQUIPAMENTOS MECÂNICOS SEGREGAÇÃO E PREPACÃO DENTRO DAS CAÇAMBAS, TRANSPORTE ATÉ O CMD PARA PESAGEM E EMISSÃO DE TICKET E TRANSPORTE ATÉ PÁTIO DE MINÉRIOS INTERNO VALE (TUBARÃO) PARA DESCARREGAMENTO - CAÇAMBAS E CAMINHÃO DA CONTRATADA. | K53: t | L53: CMS | M53: D | N53: 90 | O53: 10 | P53: 0 | Q53: 1100 | R53: =VLOOKUP(A53,CPU!D12:$H$1888,5,FALSE) -> 2857.37 | S53: =ROUND(R53*Q53,2) -> 3143107
A54: 3.4 | E54: D | F54: 70 | G54: 0 | H54: 0 | I54: 0 | J54: DESMONTAGEM DE EQUIPAMENTOS E MATERIAIS ELÉTRICOS
A55: 3.4.1 | E55: D | F55: 70 | G55: 50 | H55: 0 | I55: 0 | J55: DESMONTAGEM DE EQUIPAMENTOS E MATERIAIS ELÉTRICOS DIVERSOS
A56: 3.4.1.1 | E56: D | F56: 70 | G56: 50 | H56: 25 | I56: 20 | J56: DESMONTAGEM E/OU CARREGAMENTO, SEGREGAÇÃO E PREPARAÇÃO DENTRO DAS CAÇAMBAS DE PAINEIS, CAIXAS DE COMANDO LOCAL, CAIXAS DE INTERLIGAÇÃO, LEITOS, ELETRODUTOS, CONTROLE E INSTRUMENTAÇÃO, REMOTAS, MOTORES. CAÇAMBAS E CAMINHÃO DA CONTRATADA. | K56: t | L56: CMS | M56: D | N56: 20 | O56: 09 | P56: 000 | Q56: 135 | R56: =VLOOKUP(A56,CPU!D12:$H$1888,5,FALSE) -> 6110.58 | S56: =ROUND(R56*Q56,2) -> 824928.3
A57: 3.4.1.2 | E57: D | F57: 70 | G57: 50 | H57: 25 | I57: 30 | J57: DESMONTAGEM E/OU CARREGAMENTO, SEGREGAÇÃO E TRANSPORTE PARA DESCARTE DE REOSTATOS LÍQUIDOS E MOTORES DE MÉDIA TENSÃO. CAÇAMBAS E CAMINHÃO DA CONTRATADA. | K57: t | L57: CMS | M57: D | N57: 20 | O57: 09 | P57: 000 | Q57: 35 | R57: =VLOOKUP(A57,CPU!D12:$H$1888,5,FALSE) -> 6110.58 | S57: =ROUND(R57*Q57,2) -> 213870.3
A58: 3.4.1.3 | E58: D | F58: 70 | G58: 50 | H58: 25 | I58: 40 | J58: DESMONTAGEM E/OU CARREGAMENTO, SEGREGAÇÃO E TRANSPORTE PARA DESCARTE DE CABOS ELÉTRICOS TODAS BITOLAS. CAÇAMBAS E CAMINHÃO DA CONTRATADA. | K58: t | L58: CMS | M58: D | N58: 50 | O58: 0 | P58: 3 | Q58: 200 | R58: =VLOOKUP(A58,CPU!D12:$H$1888,5,FALSE) -> 9405.64 | S58: =ROUND(R58*Q58,2) -> 1881128
A59: 3.5 | E59: D | F59: 97 | G59: 0 | H59: 0 | I59: 0 | J59: RELOCAÇÃO DE INTERFERENCIAS, FABRICAÇÃO E MONTAGEM
A60: 3.5.1 | E60: D | F60: 97 | G60: 50 | H60: 0 | I60: 0 | J60: RELOCAÇÃO DE INTERFERENCIAS, FABRICAÇÃO E MONTAGEM-
A61: 3.5.1.1 | E61: D | F61: 97 | G61: 50 | H61: 015 | I61: 010 | J61: Relocação de interferências - Ar Comprimido - diâmetro até 4" | K61: m | L61: CMS | M61: D | N61: 97 | O61: 50 | P61: 5 | Q61: 500 | R61: =VLOOKUP(A61,CPU!D12:$H$1888,5,FALSE) -> 546.6 | S61: =ROUND(R61*Q61,2) -> 273300
A62: 3.5.1.2 | E62: D | F62: 97 | G62: 50 | H62: 015 | I62: 015 | J62: Relocação de interferências - Ar Comprimido - diâmetro maior 4" até 8" | K62: m | L62: CMS | M62: D | N62: 97 | O62: 50 | P62: 5 | Q62: 500 | R62: =VLOOKUP(A62,CPU!D12:$H$1888,5,FALSE) -> 583.98 | S62: =ROUND(R62*Q62,2) -> 291990
A63: 3.5.1.3 | E63: D | F63: 97 | G63: 50 | H63: 020 | I63: 020 | J63: Relocação de interferências - Água - diâmetro até 6" | K63: m | L63: CMS | M63: D | N63: 97 | O63: 50 | P63: 5 | Q63: 250 | R63: =VLOOKUP(A63,CPU!D12:$H$1888,5,FALSE) -> 583.98 | S63: =ROUND(R63*Q63,2) -> 145995
A64: 3.5.1.4 | E64: D | F64: 97 | G64: 50 | H64: 020 | I64: 025 | J64: Relocação de interferências - Água - diâmetro maior 6" até 8" | K64: m | L64: CMS | M64: D | N64: 97 | O64: 50 | P64: 5 | Q64: 250 | R64: =VLOOKUP(A64,CPU!D12:$H$1888,5,FALSE) -> 625.11 | S64: =ROUND(R64*Q64,2) -> 156277.5
A65: 3.5.1.5 | E65: D | F65: 97 | G65: 50 | H65: 020 | I65: 030 | J65: Relocação de interferências - Água - diâmetro maior 8" até 10" | K65: m | L65: CMS | M65: D | N65: 97 | O65: 50 | P65: 5 | Q65: 250 | R65: =VLOOKUP(A65,CPU!D12:$H$1888,5,FALSE) -> 670.34 | S65: =ROUND(R65*Q65,2) -> 167585
A66: 3.5.1.6 | E66: D | F66: 97 | G66: 50 | H66: 020 | I66: 040 | J66: Relocação de interferências - Água - diâmetro maior 10" até 12" | K66: m | L66: CMS | M66: D | N66: 97 | O66: 50 | P66: 5 | Q66: 250 | R66: =VLOOKUP(A66,CPU!D12:$H$1888,5,FALSE) -> 720.1 | S66: =ROUND(R66*Q66,2) -> 180025
A67: 3.5.1.7 | E67: D | F67: 97 | G67: 50 | H67: 030 | I67: 050 | J67: Relocação de interferências - Elétrica cabos até 25 mm² (incluindo eletroduto, bandejamento, eletrocalha e conduletes) | K67: m | L67: CMS | M67: D | N67: 97 | O67: 50 | P67: 5 | Q67: 500 | R67: =VLOOKUP(A67,CPU!D12:$H$1888,5,FALSE) -> 169.67 | S67: =ROUND(R67*Q67,2) -> 84835
A68: 3.5.1.8 | E68: D | F68: 97 | G68: 50 | H68: 030 | I68: 060 | J68: Relocação de interferências - Elétrica cabos até 10 mm² | K68: m | L68: CMS | M68: D | N68: 97 | O68: 50 | P68: 5 | Q68: 500 | R68: =VLOOKUP(A68,CPU!D12:$H$1888,5,FALSE) -> 158.77 | S68: =ROUND(R68*Q68,2) -> 79385
A69: 3.5.1.9 | E69: D | F69: 97 | G69: 50 | H69: 030 | I69: 070 | J69: Relocação de interferências - Automação - Fibra Optica | K69: m | L69: CMS | M69: D | N69: 97 | O69: 50 | P69: 5 | Q69: 250 | R69: =VLOOKUP(A69,CPU!D12:$H$1888,5,FALSE) -> 35.6 | S69: =ROUND(R69*Q69,2) -> 8900
A70: 3.5.1.10 | E70: D | F70: 97 | G70: 50 | H70: 030 | I70: 080 | J70: Fusão em cabo de fibra optica | K70: UNID. | L70: CMS | M70: C | N70: 70 | O70: 21 | P70: 000 | Q70: =250/5 -> 50 | R70: =VLOOKUP(A70,CPU!D12:$H$1888,5,FALSE) -> 560.86 | S70: =ROUND(R70*Q70,2) -> 28043
A71: 3.5.1.11 | E71: D | F71: 97 | G71: 50 | H71: 030 | I71: 090 | J71: Relocação de interferências - Eletrocalhas 200 x 75 mm galvanizada a fogo | K71: m | L71: CMS | M71: D | N71: 97 | O71: 50 | P71: 5 | Q71: 1000 | R71: =VLOOKUP(A71,CPU!D12:$H$1888,5,FALSE) -> 32.91 | S71: =ROUND(R71*Q71,2) -> 32910
A72: 3.5.1.12 | E72: D | F72: 97 | G72: 50 | H72: 030 | I72: 100 | J72: Relocação de Guarda-corpos provenientes de desemontagem que seriam descartadados para corrigir condição insegura. | K72: m | L72: CMS | M72: D | N72: 97 | O72: 50 | P72: 5 | Q72: 50 | R72: =VLOOKUP(A72,CPU!D12:$H$1888,5,FALSE) -> 1438.48 | S72: =ROUND(R72*Q72,2) -> 71924
A73: 3.6 | E73: D | F73: 98 | G73: 0 | H73: 0 | I73: 0 | J73: DESMONTAGEM DE MATERIAIS
A74: 3.6.1 | E74: D | F74: 98 | G74: 50 | H74: 0 | I74: 0 | J74: DESMONTAGEM DE MATERIAIS NÃO METÁLICOS
A75: 3.6.1.1 | E75: D | F75: 98 | G75: 50 | H75: 020 | I75: 010 | J75: DESMONTAGEM E/OU CARREGAMENTO, SEGREGAÇÃO E PREPARAÇÃO DENTRO DAS CAÇAMBAS DE TELHAS FIBRICIMENTO. CAÇAMBAS E CAMINHÃO DA CONTRATADA. | K75: t | L75: CMS | M75: D | N75: 50 | O75: 0 | P75: 2 | Q75: 1 | R75: =VLOOKUP(A75,CPU!D12:$H$1888,5,FALSE) -> 37472.06 | S75: =ROUND(R75*Q75,2) -> 37472.06
A76: 3.6.1.2 | E76: D | F76: 98 | G76: 50 | H76: 020 | I76: 015 | J76: DESMONTAGEM E/OU CARREGAMENTO, SEGREGAÇÃO E PREPARAÇÃO DENTRO DAS CAÇAMBAS DE MATERIAL PLASTICOS. CAÇAMBAS E CAMINHÃO DA CONTRATADA. | K76: t | L76: CMS | M76: D | N76: 50 | O76: 0 | P76: 2 | Q76: 1 | R76: =VLOOKUP(A76,CPU!D12:$H$1888,5,FALSE) -> 37075.7 | S76: =ROUND(R76*Q76,2) -> 37075.7
A77: 3.6.1.3 | E77: D | F77: 98 | G77: 50 | H77: 020 | I77: 020 | J77: DESMONTAGEM E/OU CARREGAMENTO, SEGREGAÇÃO E PREPARAÇÃO DENTRO DAS CAÇAMBAS DE MATERIAL EM BORRACHA. CAÇAMBAS E CAMINHÃO DA CONTRATADA. | K77: t | L77: CMS | M77: D | N77: 50 | O77: 0 | P77: 2 | Q77: 15 | R77: =VLOOKUP(A77,CPU!D13:$H$1888,5,FALSE) -> 19203.45 | S77: =ROUND(R77*Q77,2) -> 288051.75
A78: 3.6.1.4 | E78: D | F78: 98 | G78: 50 | H78: 020 | I78: 025 | J78: DESMONTAGEM E/OU CARREGAMENTO, SEGREGAÇÃO E PREPARAÇÃO DENTRO DAS CAÇAMBAS DE MATERIAL EM MADEIRA. CAÇAMBAS E CAMINHÃO DA CONTRATADA. | K78: t | L78: CMS | M78: D | N78: 50 | O78: 0 | P78: 2 | Q78: 0.5 | R78: =VLOOKUP(A78,CPU!D14:$H$1888,5,FALSE) -> 37075.7 | S78: =ROUND(R78*Q78,2) -> 18537.85
A79: 4 | E79: F | F79: 0 | G79: 0 | H79: 0 | I79: 0 | J79: FORNECIMENTO DE EQUIPAMENTOS E COMPONENTES ELETROMECÂNICOS
A80: 4.1 | E80: F | F80: 60 | G80: 0 | H80: 0 | I80: 0 | J80: FORNECIMENTO DE TUBO, CONEXÕES, VÁLVULAS E ACESSÒRIOS
A81: 4.1.1 | E81: F | F81: 60 | G81: 10 | H81: 000 | I81: 000 | J81: FORNECIMENTO DE TUBULAÇÕES
A82: 4.1.1.1. | E82: F | F82: 60 | G82: 10 | H82: 810 | I82: 0 | J82: Fornecimento de tubo de Aço Carbono ASTM A 53 Gr B-S, SCH.STD. WT, C /Extr. para Solda de Topo - FORNECIMENTO DE TUBO AÇO CARBONO ASTM A 53 Gr B-S, SCH.STD. WT, C /Extr. PARA SOLDA DE TOPO
A83: 4.1.1.1.1 | E83: F | F83: 60 | G83: 10 | H83: 30 | I83: 15 | J83: Fornecimento de tubo de Aço Carbono ASTM A 53 Gr B-S, SCH.STD. WT, C /Extr. para Solda de Topo - Ar Comprimido - diâmetro até 4" para retiradas de interferências incluído conexões, suportes, válvulas etc. | K83: m | L83: CMS | M83: F | N83: 60 | O83: 10 | P83: 0 | Q83: =Q61/4 -> 125 | R83: =VLOOKUP(A83,CPU!D19:$H$1888,5,FALSE) -> 594.72 | S83: =ROUND(R83*Q83,2) -> 74340
A84: 4.1.1.1.2 | E84: F | F84: 60 | G84: 10 | H84: =H83 -> 30 | I84: 25 | J84: Fornecimento de tubo de Aço Carbono ASTM A 53 Gr B-S, SCH.STD. WT, C /Extr. para Solda de Topo - Ar Comprimido - diâmetro maior que 4" até 8" para retiradas de interferências incluído conexões, suportes, válvulas etc. | K84: m | L84: CMS | M84: F | N84: 60 | O84: 10 | P84: 0 | Q84: =Q62/4 -> 125 | R84: =VLOOKUP(A84,CPU!D20:$H$1888,5,FALSE) -> 1433.27 | S84: =ROUND(R84*Q84,2) -> 179158.75
A85: 4.1.1.1.3 | E85: F | F85: 60 | G85: 10 | H85: =H84 -> 30 | I85: 20 | J85: Fornecimento de tubo de Aço Carbono ASTM A 53 Gr B-S, SCH.STD. WT, C /Extr. para Solda de Topo - Água - diâmetro até 6" para retiradas de interferências incluído conexões, suportes, válvulas etc. | K85: m | L85: CMS | M85: F | N85: 60 | O85: 10 | P85: 0 | Q85: =Q63/4 -> 62.5 | R85: =VLOOKUP(A85,CPU!D21:$H$1888,5,FALSE) -> 1433.27 | S85: =ROUND(R85*Q85,2) -> 89579.38
A86: 4.1.1.1.4 | E86: F | F86: 60 | G86: 10 | H86: =H85 -> 30 | I86: 25 | J86: Fornecimento de tubo de Aço Carbono ASTM A 53 Gr B-S, SCH.STD. WT, C /Extr. para Solda de Topo - Água - diâmetro maior que 6" até 8" para retiradas de interferências incluído conexões, suportes, válvulas etc. | K86: m | L86: CMS | M86: F | N86: 60 | O86: 10 | P86: 0 | Q86: =Q64/4 -> 62.5 | R86: =VLOOKUP(A86,CPU!D22:$H$1888,5,FALSE) -> 1863.98 | S86: =ROUND(R86*Q86,2) -> 116498.75
A87: 4.1.1.1.5 | E87: F | F87: 60 | G87: 10 | H87: =H86 -> 30 | I87: 30 | J87: Fornecimento de tubode Aço Carbono ASTM A 53 Gr B-S, SCH.STD. WT, C /Extr. para Solda de Topo - Água - diâmetro maior que 8" até 10" para retiradas de interferências incluído conexões, suportes, válvulas etc. | K87: m | L87: CMS | M87: F | N87: 60 | O87: 10 | P87: 0 | Q87: =Q65/4 -> 62.5 | R87: =VLOOKUP(A87,CPU!D23:$H$1888,5,FALSE) -> 2143.58 | S87: =ROUND(R87*Q87,2) -> 133973.75
A88: 4.1.1.1.6 | E88: F | F88: 60 | G88: 10 | H88: =H87 -> 30 | I88: 35 | J88: Fornecimento de tubode Aço Carbono ASTM A 53 Gr B-S, SCH.STD. WT, C /Extr. para Solda de Topo - Água - diâmetro maior que 10" até 12" para retiradas de interferências incluído conexões, suportes, válvulas etc. | K88: m | L88: CMS | M88: F | N88: 60 | O88: 10 | P88: 0 | Q88: =Q66/4 -> 62.5 | R88: =VLOOKUP(A88,CPU!D24:$H$1888,5,FALSE) -> 3982.88 | S88: =ROUND(R88*Q88,2) -> 248930
A89: 4.2 | E89: F | F89: 75 | G89: 0 | H89: 0 | I89: 0 | J89: FORNECIMENTO DE ESTRUTURA METÁLICA
A90: 4.2.1 | E90: F | F90: 75 | G90: 10 | H90: 0 | I90: 0 | J90: FORNECIMENTO DE ESTRUTURAS METÁLICAS
A91: 4.2.1.1. | E91: F | F91: 75 | G91: 10 | H91: 15 | I91: 0 | J91: FORNECIMENTO DE ESTRUTURAS METÁLICAS E CALDEIRARIA LEVE, MÉDIA E PESADA
A92: 4.2.1.1.1 | E92: F | F92: 75 | G92: 10 | H92: 10 | I92: 4 | J92: FABRICAÇÃO E FORNECIMENTO DE ESTRUTURAS METÁLICAS - GUARDA-CORPOS E CONDIÇÕES INSEGURAS- Conforme padrão Vale. | K92: t | L92: CMS | M92: F | N92: 75 | O92: 10 | P92: 0 | Q92: 2 | R92: =VLOOKUP(A92,CPU!D28:$H$1888,5,FALSE) -> 44707.97 | S92: =ROUND(R92*Q92,2) -> 89415.94
A93: 5 | E93: M | F93: 0 | G93: 0 | H93: 0 | I93: 0 | J93: MONTAGEM DE EQUIPAMENTOS E COMPONENTES ELETROMECÂNICOS
A94: 5.1 | E94: M | F94: 60 | G94: 0 | H94: 0 | I94: 0 | J94: MONTAGEM DE TUBO, CONEXÕES, VÁLVULAS E ACESSÒRIOS
A95: 5.1.1 | E95: M | F95: 60 | G95: 10 | H95: 0 | I95: 0 | J95: MONTAGEM DE TUBO
A96: 5.1.1.1. | E96: M | F96: 60 | G96: 10 | H96: 30 | I96: 0 | J96: MONTAGEM DE TUBO EM AÇO CARBONO
A97: 5.1.1.1.1 | E97: =E106 -> M | F97: 60 | G97: =G106 -> 10 | H97: =H83 -> 30 | I97: =I83 -> 15 | J97: MONTAGEM de tubo de Aço Carbono ASTM A 53 Gr B-S, SCH.STD. WT, C /Extr. para Solda de Topo - Ar Comprimido - diâmetro até 4" para retiradas de interferências incluído conexões, suportes, válvulas etc. | K97: =K83 -> m | L97: =L83 -> CMS | M97: =M106 -> M | N97: =N83 -> 60 | O97: =O83 -> 10 | P97: 0 | Q97: =Q83 -> 125 | R97: =VLOOKUP(A97,CPU!D33:$H$1888,5,FALSE) -> 1230.17 | S97: =ROUND(R97*Q97,2) -> 153771.25
A98: 5.1.1.1.2 | E98: =E97 -> M | F98: =F97 -> 60 | G98: =G97 -> 10 | H98: =H84 -> 30 | I98: =I84 -> 25 | J98: MONTAGEM de tubo de Aço Carbono ASTM A 53 Gr B-S, SCH.STD. WT, C /Extr. para Solda de Topo - Ar Comprimido - diâmetro maior que 4" até 8" para retiradas de interferências incluído conexões, suportes, válvulas etc. | K98: =K84 -> m | L98: =L84 -> CMS | M98: =M97 -> M | N98: =N84 -> 60 | O98: =O84 -> 10 | P98: 0 | Q98: =Q84 -> 125 | R98: =VLOOKUP(A98,CPU!D34:$H$1888,5,FALSE) -> 1338.03 | S98: =ROUND(R98*Q98,2) -> 167253.75
A99: 5.1.1.1.3 | E99: =E98 -> M | F99: =F98 -> 60 | G99: =G98 -> 10 | H99: =H85 -> 30 | I99: =I85 -> 20 | J99: MONTAGEM de tubo de Aço Carbono ASTM A 53 Gr B-S, SCH.STD. WT, C /Extr. para Solda de Topo - Água - diâmetro até 6" para retiradas de interferências incluído conexões, suportes, válvulas etc. | K99: =K85 -> m | L99: =L85 -> CMS | M99: =M98 -> M | N99: =N85 -> 60 | O99: =O85 -> 10 | P99: 0 | Q99: =Q85 -> 62.5 | R99: =VLOOKUP(A99,CPU!D35:$H$1888,5,FALSE) -> 1338.03 | S99: =ROUND(R99*Q99,2) -> 83626.88
A100: 5.1.1.1.4 | E100: =E99 -> M | F100: =F99 -> 60 | G100: =G99 -> 10 | H100: =H86 -> 30 | I100: =I86 -> 25 | J100: MONTAGEM de tubo de Aço Carbono ASTM A 53 Gr B-S, SCH.STD. WT, C /Extr. para Solda de Topo - Água - diâmetro maior que 6" até 8" para retiradas de interferências incluído conexões, suportes, válvulas etc. | K100: =K86 -> m | L100: =L86 -> CMS | M100: =M99 -> M | N100: =N86 -> 60 | O100: =O86 -> 10 | P100: 0 | Q100: =Q86 -> 62.5 | R100: =VLOOKUP(A100,CPU!D36:$H$1888,5,FALSE) -> 1519.82 | S100: =ROUND(R100*Q100,2) -> 94988.75
A101: 5.1.1.1.5 | E101: =E100 -> M | F101: =F100 -> 60 | G101: =G100 -> 10 | H101: =H87 -> 30 | I101: =I87 -> 30 | J101: MONTAGEM de tubode Aço Carbono ASTM A 53 Gr B-S, SCH.STD. WT, C /Extr. para Solda de Topo - Água - diâmetro maior que 8" até 10" para retiradas de interferências incluído conexões, suportes, válvulas etc. | K101: =K87 -> m | L101: =L87 -> CMS | M101: =M100 -> M | N101: =N87 -> 60 | O101: =O87 -> 10 | P101: 0 | Q101: =Q87 -> 62.5 | R101: =VLOOKUP(A101,CPU!D37:$H$1888,5,FALSE) -> 1519.82 | S101: =ROUND(R101*Q101,2) -> 94988.75
A102: 5.1.1.1.6 | E102: =E101 -> M | F102: =F101 -> 60 | G102: =G101 -> 10 | H102: =H88 -> 30 | I102: =I88 -> 35 | J102: MONTAGEM de tubode Aço Carbono ASTM A 53 Gr B-S, SCH.STD. WT, C /Extr. para Solda de Topo - Água - diâmetro maior que 10" até 12" para retiradas de interferências incluído conexões, suportes, válvulas etc. | K102: =K88 -> m | L102: =L88 -> CMS | M102: =M101 -> M | N102: =N88 -> 60 | O102: =O88 -> 10 | P102: 0 | Q102: =Q88 -> 62.5 | R102: =VLOOKUP(A102,CPU!D38:$H$1888,5,FALSE) -> 2533.81 | S102: =ROUND(R102*Q102,2) -> 158363.13
...

Sheet CPU
A3: X | C3: GERAL
C5: SERVIÇO: | D5: Mobilização de equipe e equipamentos
C6: ITEM: | D6: 1.1.1.1.1 | F6: UNID.: | G6: vb | H6: 0
C7: ITEM | D7: DESCRIÇÃO | E7: UNID | F7: QUANTIDADE | G7: VALOR UNIT. | H7: VALOR TOTAL
C9: 1.0 | D9: MÃO DE OBRA
G11: 0
G12: 0 | H12: 0
C13: TOTAL 1.0 | H13: 0
C14: 2.0 | D14: EQUIPAMENTOS
G15: 0 | H15: 0
G16: 0 | H16: 0
G17: 0 | H17: 0
G18: 0 | H18: 0
G19: 0 | H19: 0
G20: 0 | H20: 0
G21: 0 | H21: 0
G22: 0 | H22: 0
C23: TOTAL 2.0 | H23: 0
C24: 3.0 | D24: MATERIAIS | H24: 0
G25: 0 | H25: 0
G26: 0 | H26: 0
G27: 0 | H27: 0
G28: 0 | H28: 0
G29: 0 | H29: 0
G30: 0 | H30: 0
G31: 0 | H31: 0
C32: TOTAL 3.0 | H32: 0
C33: CUSTO DIRETO (A+B+C) | H33: 0
C34: BDI | H34: 0
C35: TOTAL GERAL | H35: 0
C37: SERVIÇO: | D37: Desmobilização de equipe e equipamentos
C38: ITEM: | D38: 1.1.1.1.2 | F38: UNID.: | G38: vb | H38: 268104.35
C39: ITEM | D39: DESCRIÇÃO | E39: UNID | F39: QUANTIDADE | G39: VALOR UNIT. | H39: VALOR TOTAL
C41: 1.0 | D41: MÃO DE OBRA
C42: MOD | D42: Mecânico montador | E42: h | F42: 330 | G42: 79.456006 | H42: 26220.482
C43: MOD | D43: Ajudante de montagem | E43: h | F43: 330 | G43: 45.411751 | H43: 14985.878
G44: 0 | H44: 0
G45: 0 | H45: 0
C46: TOTAL 1.0 | H46: 41206.36
C47: 2.0 | D47: EQUIPAMENTOS
C48: EQUIP | D48: REPAROS E IDENIZAÇÕES EM EQUIPAMENTOS DE PEQUENO E MÉDIO PORTE | E48: VB | F48: 1 | G48: 100000 | H48: 100000
G50: 0 | H50: 0
G51: 0 | H51: 0
G52: 0 | H52: 0
G53: 0 | H53: 0
G54: 0 | H54: 0
G55: 0 | H55: 0
C56: TOTAL 2.0 | H56: 100000
C57: 3.0 | D57: MATERIAIS | H57: 0
D58: Exames demissionais | H58: 0
C59: MAT/MOD | D59: Equipe MOD | E59: und | F59: 136 | G59: 450 | H59: 61200
C60: MAT/MOD | D60: Equipe MOI | E60: und | F60: 33 | G60: 385 | H60: 12705
G61: 0 | H61: 0
G62: 0 | H62: 0
G63: 0 | H63: 0
C64: TOTAL 3.0 | H64: 73905
C65: CUSTO DIRETO (A+B+C) | H65: 215111.36
C66: BDI | H66: 52992.991
C67: TOTAL GERAL | H67: 268104.35
C69: SERVIÇO: | D69: Construção de Canteiro Completo (Adm, Vestiários, Refeitório, Armazém, etc)
C70: ITEM: | D70: 1.2.1.1 | F70: UNID.: | G70: vb | H70: 0
C71: ITEM | D71: DESCRIÇÃO | E71: UNID | F71: QUANTIDADE | G71: VALOR UNIT. | H71: VALOR TOTAL
C73: 1.0 | D73: MÃO DE OBRA
G80: 0 | H80: 0
G81: 0 | H81: 0
G82: 0 | H82: 0
G83: 0 | H83: 0
G84: 0 | H84: 0
C85: TOTAL 1.0 | H85: 0
C86: 2.0 | D86: EQUIPAMENTOS
G88: 0 | H88: 0
G89: 0 | H89: 0
C90: TOTAL 2.0 | H90: 0
C91: 3.0 | D91: MATERIAIS | H91: 0
G113: 0 | H113: 0
G114: 0 | H114: 0
G115: 0 | H115: 0
G116: 0 | H116: 0
C117: TOTAL 3.0 | H117: 0
C118: CUSTO DIRETO (A+B+C) | H118: 0
C119: BDI | H119: 0
C120: TOTAL GERAL | H120: 0
C122: SERVIÇO: | D122: Administração e Manutenção de Canteiro
C123: ITEM: | D123: 1.2.1.2 | F123: UNID.: | G123: vb x mês | H123: 122923.33
C124: ITEM | D124: DESCRIÇÃO | E124: UNID | F124: QUANTIDADE | G124: VALOR UNIT. | H124: VALOR TOTAL
C126: 1.0 | D126: MÃO DE OBRA
D127: Manutenção de Canteiro | H127: 0
C128: MOD | D128: Auxiliar de serviços gerais | E128: h | F128: 132 | G128: 44.933633 | H128: 5931.2396
C129: TOTAL 1.0 | H129: 5931.2396
C130: 2.0 | D130: EQUIPAMENTOS
C131: EQUIP | D131: Contêiner Almoxarifado - 6m | E131: qnt x mês | F131: 2 | G131: 1089 | H131: 2178
C132: EQUIP | D132: Contêiner Módulo Habitável Escritório - 6m | E132: qnt x mês | F132: 5 | G132: 1089 | H132: 5445
C133: EQUIP | D133: Contêiner Módulo Habitável Vestiário - 6m | E133: qnt x mês | F133: 2 | G133: 1628 | H133: 3256
C134: EQUIP | D134: Contêiner Módulo Habitável Sanitário com chuveiros - 6m | E134: qnt x mês | F134: 1 | G134: 1699.5 | H134: 1699.5
C135: EQUIP | D135: Contêiner Módulo Habitável Sanitário com vasos - 6m | E135: qnt x mês | F135: 3 | G135: 1699.5 | H135: 5098.5
C136: EQUIP | D136: Banheiros hidráulicos | E136: qnt x mês | F136: 8 | G136: 850 | H136: 6800
C137: EQUIP | D137: Limpeza banheiros hidráulicos | E137: vb | F137: 1 | G137: 8000 | H137: 8000
C138: EQUIP | D138: Caminhão pipa com operador | E138: qnt x mês | F138: 1 | G138: 24268.303 | H138: 24268.303
C139: TOTAL 2.0 | H139: 56745.303
C140: 3.0 | D140: MATERIAIS | H140: 0
...

Sheet MO
B1: EQUIPE TÉCNICA | E1: EQUIPE TÉCNICA | H1: EQUIPE TÉCNICA | K1: EQUIPE TÉCNICA | N1: SUPERVISÃO | Q1: SUPERVISÃO | T1: SUPERVISÃO | W1: SUPERVISÃO | Z1: SUPERVISÃO | AC1: EQUIPE TÉCNICA | AF1: EQUIPE TÉCNICA | AI1: EQUIPE TÉCNICA | AL1: EQUIPE TÉCNICA | AO1: EQUIPE TÉCNICA | AR1: EQUIPE TÉCNICA | AU1: EQUIPE TÉCNICA | AX1: EQUIPE TÉCNICA | BA1: EQUIPE TÉCNICA | BD1: EQUIPE TÉCNICA | BG1: EQUIPE TÉCNICA | BJ1: EQUIPE TÉCNICA | BM1: EQUIPE TÉCNICA | BP1: EQUIPE TÉCNICA | BS1: EQUIPE TÉCNICA | BV1: EQUIPE TÉCNICA | BY1: EQUIPE TÉCNICA | CB1: EQUIPE DIRETA | CE1: EQUIPE DIRETA | CH1: EQUIPE DIRETA | CK1: EQUIPE DIRETA | CN1: EQUIPE DIRETA | CQ1: EQUIPE DIRETA | CT1: EQUIPE DIRETA | CW1: EQUIPE DIRETA | CZ1: EQUIPE DIRETA | DC1: EQUIPE DIRETA | DF1: EQUIPE DIRETA | DI1: EQUIPE DIRETA | DL1: EQUIPE DIRETA | DO1: EQUIPE DIRETA | DR1: EQUIPE DIRETA | DU1: EQUIPE DIRETA | DX1: EQUIPE DIRETA | EA1: EQUIPE DIRETA | ED1: EQUIPE DIRETA | EG1: EQUIPE DIRETA | EJ1: EQUIPE DIRETA
B2: COMPOSIÇÃO DO CUSTO MENSAL DE MÃO-DE-OBRA | E2: COMPOSIÇÃO DO CUSTO MENSAL DE MÃO-DE-OBRA | H2: COMPOSIÇÃO DO CUSTO MENSAL DE MÃO-DE-OBRA - TURNO 1 | K2: COMPOSIÇÃO DO CUSTO MENSAL DE MÃO-DE-OBRA | N2: COMPOSIÇÃO DO CUSTO MENSAL DE MÃO-DE-OBRA - TURNO 1 | Q2: COMPOSIÇÃO DO CUSTO MENSAL DE MÃO-DE-OBRA - TURNO 1 | T2: COMPOSIÇÃO DO CUSTO MENSAL DE MÃO-DE-OBRA - TURNO 1 | W2: COMPOSIÇÃO DO CUSTO MENSAL DE MÃO-DE-OBRA - TURNO 1 | Z2: COMPOSIÇÃO DO CUSTO MENSAL DE MÃO-DE-OBRA - TURNO 1 | AC2: COMPOSIÇÃO DO CUSTO MENSAL DE MÃO-DE-OBRA | AF2: COMPOSIÇÃO DO CUSTO MENSAL DE MÃO-DE-OBRA | AI2: COMPOSIÇÃO DO CUSTO MENSAL DE MÃO-DE-OBRA | AL2: COMPOSIÇÃO DO CUSTO MENSAL DE MÃO-DE-OBRA - TURNO 1 | AO2: COMPOSIÇÃO DO CUSTO MENSAL DE MÃO-DE-OBRA - TURNO 1 | AR2: COMPOSIÇÃO DO CUSTO MENSAL DE MÃO-DE-OBRA - TURNO 1 | AU2: COMPOSIÇÃO DO CUSTO MENSAL DE MÃO-DE-OBRA - TURNO 1 | AX2: COMPOSIÇÃO DO CUSTO MENSAL DE MÃO-DE-OBRA | BA2: COMPOSIÇÃO DO CUSTO MENSAL DE MÃO-DE-OBRA | BD2: COMPOSIÇÃO DO CUSTO MENSAL DE MÃO-DE-OBRA - TURNO 1 | BG2: COMPOSIÇÃO DO CUSTO MENSAL DE MÃO-DE-OBRA - TURNO 1 | BJ2: COMPOSIÇÃO DO CUSTO MENSAL DE MÃO-DE-OBRA - TURNO 1 | BM2: COMPOSIÇÃO DO CUSTO MENSAL DE MÃO-DE-OBRA - TURNO 1 | BP2: COMPOSIÇÃO DO CUSTO MENSAL DE MÃO-DE-OBRA - TURNO 1 | BS2: COMPOSIÇÃO DO CUSTO MENSAL DE MÃO-DE-OBRA - TURNO 1 | BV2: COMPOSIÇÃO DO CUSTO MENSAL DE MÃO-DE-OBRA - TURNO 1 | BY2: COMPOSIÇÃO DO CUSTO MENSAL DE MÃO-DE-OBRA - TURNO 1 | CB2: COMPOSIÇÃO DO CUSTO MENSAL DE MÃO-DE-OBRA - TURNO 1 | CE2: COMPOSIÇÃO DO CUSTO MENSAL DE MÃO-DE-OBRA - TURNO 1 | CH2: COMPOSIÇÃO DO CUSTO MENSAL DE MÃO-DE-OBRA - TURNO 1 | CK2: COMPOSIÇÃO DO CUSTO MENSAL DE MÃO-DE-OBRA - TURNO 1 | CN2: COMPOSIÇÃO DO CUSTO MENSAL DE MÃO-DE-OBRA - TURNO 1 | CQ2: COMPOSIÇÃO DO CUSTO MENSAL DE MÃO-DE-OBRA - TURNO 1 | CT2: COMPOSIÇÃO DO CUSTO MENSAL DE MÃO-DE-OBRA - TURNO 1 | CW2: COMPOSIÇÃO DO CUSTO MENSAL DE MÃO-DE-OBRA - TURNO 1 | CZ2: COMPOSIÇÃO DO CUSTO MENSAL DE MÃO-DE-OBRA - TURNO 1 | DC2: COMPOSIÇÃO DO CUSTO MENSAL DE MÃO-DE-OBRA - TURNO 1 | DF2: COMPOSIÇÃO DO CUSTO MENSAL DE MÃO-DE-OBRA - TURNO 1 | DI2: COMPOSIÇÃO DO CUSTO MENSAL DE MÃO-DE-OBRA - TURNO 1 | DL2: COMPOSIÇÃO DO CUSTO MENSAL DE MÃO-DE-OBRA - TURNO 1 | DO2: COMPOSIÇÃO DO CUSTO MENSAL DE MÃO-DE-OBRA - TURNO 1 | DR2: COMPOSIÇÃO DO CUSTO MENSAL DE MÃO-DE-OBRA - TURNO 1 | DU2: COMPOSIÇÃO DO CUSTO MENSAL DE MÃO-DE-OBRA - TURNO 1 | DX2: COMPOSIÇÃO DO CUSTO MENSAL DE MÃO-DE-OBRA - TURNO 1 | EA2: COMPOSIÇÃO DO CUSTO MENSAL DE MÃO-DE-OBRA - TURNO 1 | ED2: COMPOSIÇÃO DO CUSTO MENSAL DE MÃO-DE-OBRA - TURNO 1 | EG2: COMPOSIÇÃO DO CUSTO MENSAL DE MÃO-DE-OBRA - TURNO 1 | EJ2: COMPOSIÇÃO DO CUSTO MENSAL DE MÃO-DE-OBRA - TURNO 1
B3: QUADRO DE COMPOSIÇÃO DO CUSTO DA MÃO-DE-OBRA | E3: QUADRO DE COMPOSIÇÃO DO CUSTO DA MÃO-DE-OBRA | H3: QUADRO DE COMPOSIÇÃO DO CUSTO DA MÃO-DE-OBRA | K3: QUADRO DE COMPOSIÇÃO DO CUSTO DA MÃO-DE-OBRA | N3: QUADRO DE COMPOSIÇÃO DO CUSTO DA MÃO-DE-OBRA | Q3: QUADRO DE COMPOSIÇÃO DO CUSTO DA MÃO-DE-OBRA | T3: QUADRO DE COMPOSIÇÃO DO CUSTO DA MÃO-DE-OBRA | W3: QUADRO DE COMPOSIÇÃO DO CUSTO DA MÃO-DE-OBRA | Z3: QUADRO DE COMPOSIÇÃO DO CUSTO DA MÃO-DE-OBRA | AC3: QUADRO DE COMPOSIÇÃO DO CUSTO DA MÃO-DE-OBRA | AF3: QUADRO DE COMPOSIÇÃO DO CUSTO DA MÃO-DE-OBRA | AI3: QUADRO DE COMPOSIÇÃO DO CUSTO DA MÃO-DE-OBRA | AL3: QUADRO DE COMPOSIÇÃO DO CUSTO DA MÃO-DE-OBRA | AO3: QUADRO DE COMPOSIÇÃO DO CUSTO DA MÃO-DE-OBRA | AR3: QUADRO DE COMPOSIÇÃO DO CUSTO DA MÃO-DE-OBRA | AU3: QUADRO DE COMPOSIÇÃO DO CUSTO DA MÃO-DE-OBRA | AX3: QUADRO DE COMPOSIÇÃO DO CUSTO DA MÃO-DE-OBRA | BA3: QUADRO DE COMPOSIÇÃO DO CUSTO DA MÃO-DE-OBRA | BD3: QUADRO DE COMPOSIÇÃO DO CUSTO DA MÃO-DE-OBRA | BG3: QUADRO DE COMPOSIÇÃO DO CUSTO DA MÃO-DE-OBRA | BJ3: QUADRO DE COMPOSIÇÃO DO CUSTO DA MÃO-DE-OBRA | BM3: QUADRO DE COMPOSIÇÃO DO CUSTO DA MÃO-DE-OBRA | BP3: QUADRO DE COMPOSIÇÃO DO CUSTO DA MÃO-DE-OBRA | BS3: QUADRO DE COMPOSIÇÃO DO CUSTO DA MÃO-DE-OBRA | BV3: QUADRO DE COMPOSIÇÃO DO CUSTO DA MÃO-DE-OBRA | BY3: QUADRO DE COMPOSIÇÃO DO CUSTO DA MÃO-DE-OBRA | CB3: QUADRO DE COMPOSIÇÃO DO CUSTO DA MÃO-DE-OBRA | CE3: QUADRO DE COMPOSIÇÃO DO CUSTO DA MÃO-DE-OBRA | CH3: QUADRO DE COMPOSIÇÃO DO CUSTO DA MÃO-DE-OBRA | CK3: QUADRO DE COMPOSIÇÃO DO CUSTO DA MÃO-DE-OBRA | CN3: QUADRO DE COMPOSIÇÃO DO CUSTO DA MÃO-DE-OBRA | CQ3: QUADRO DE COMPOSIÇÃO DO CUSTO DA MÃO-DE-OBRA | CT3: QUADRO DE COMPOSIÇÃO DO CUSTO DA MÃO-DE-OBRA | CW3: QUADRO DE COMPOSIÇÃO DO CUSTO DA MÃO-DE-OBRA | CZ3: QUADRO DE COMPOSIÇÃO DO CUSTO DA MÃO-DE-OBRA | DC3: QUADRO DE COMPOSIÇÃO DO CUSTO DA MÃO-DE-OBRA | DF3: QUADRO DE COMPOSIÇÃO DO CUSTO DA MÃO-DE-OBRA | DI3: QUADRO DE COMPOSIÇÃO DO CUSTO DA MÃO-DE-OBRA | DL3: QUADRO DE COMPOSIÇÃO DO CUSTO DA MÃO-DE-OBRA | DO3: QUADRO DE COMPOSIÇÃO DO CUSTO DA MÃO-DE-OBRA | DR3: QUADRO DE COMPOSIÇÃO DO CUSTO DA MÃO-DE-OBRA | DU3: QUADRO DE COMPOSIÇÃO DO CUSTO DA MÃO-DE-OBRA | DX3: QUADRO DE COMPOSIÇÃO DO CUSTO DA MÃO-DE-OBRA | EA3: QUADRO DE COMPOSIÇÃO DO CUSTO DA MÃO-DE-OBRA | ED3: QUADRO DE COMPOSIÇÃO DO CUSTO DA MÃO-DE-OBRA | EG3: QUADRO DE COMPOSIÇÃO DO CUSTO DA MÃO-DE-OBRA | EJ3: QUADRO DE COMPOSIÇÃO DO CUSTO DA MÃO-DE-OBRA
B4: GERENTE | C4: VALOR R$ | E4: ENGENHEIRO MECÂNICO / CIVIL / PRODUÇÃO / PROCESSOS | F4: VALOR R$ | H4: ENGENHEIRO DE PLANEJAMENTO | I4: VALOR R$ | K4: ENGENHEIRO ELETRICISTA | L4: VALOR R$ | N4: SUPERVISOR CIVIL/MECÂNICA/MONTAGEM | O4: VALOR R$ | Q4: SUPERVISOR ELÉTRICA | R4: VALOR R$ | T4: ENCARREGADO CIVIL / ANDAIME | U4: VALOR R$ | W4: MESTRE DE MONTAGEM | X4: VALOR R$ | Z4: ENCARREGADO ELÉTRICA | AA4: VALOR R$ | AC4: TÉCNICO DE PRODUÇÃO / ANALISTA DE PROJETOS | AD4: VALOR R$ | AF4: TÉCNICO DE PLANEJAMENTO / MEDIÇÃO / QUALIDADE / MATERIAIS | AG4: VALOR R$ | AI4: AUXILIAR DE ENGENHARIA/PLANEJAMENTO/MEIO AMBIENTE/QUALIDADE | AJ4: VALOR R$ | AL4: TÉCNICO DE MEIO AMBIENTE | AM4: VALOR R$ | AO4: TÉCNICO DE AUTOMAÇÃO / ELÉTRICA | AP4: VALOR R$ | AR4: ADMINISTRATIVO | AS4: VALOR R$ | AU4: AUXILIAR ADMINISTRATIVO | AV4: VALOR R$ | AX4: ENG SEGURANÇA TRABALHO | AY4: VALOR R$ | BA4: MÉDICO TRABALHO (PART TIME) | BB4: VALOR R$ | BD4: TÉCNICO SEGURANÇA TRABALHO LIDER | BE4: VALOR R$ | BG4: Técnico em Segurança do Trabalho Campo | BH4: VALOR R$ | BJ4: ALMOXARIFE | BK4: VALOR R$ | BM4: AUXILIAR ALMOXARIFE | BN4: VALOR R$ | BP4: TOPOGRAFO | BQ4: VALOR R$ | BS4: AUXILIAR TOPOGRAFO | BT4: VALOR R$ | BV4: MOTORISTA DE VEICULOS LEVES | BW4: VALOR R$ | BY4: TÉCNICO ENFERMAGEM | BZ4: VALOR R$ | CB4: ELETRICISTA MONTADOR | CC4: VALOR R$ | CE4: ELETRICISTA MANUTENÇÃO | CF4: VALOR R$ | CH4: AJUDANTE ELETRICISTA | CI4: VALOR R$ | CK4: POLIVALENTE | CL4: VALOR R$ | CN4: AUXILIAR DE OBRAS | CO4: VALOR R$ | CQ4: CALDEIREIRO | CR4: VALOR R$ | CT4: SOLDADOR TIG | CU4: VALOR R$ | CW4: ELETRICISTA F/C | CX4: VALOR R$ | CZ4: MECÂNICO MONTADOR | DA4: VALOR R$ | DC4: MECÂNICO MONTADOR/LUBRIFICADOR | DD4: VALOR R$ | DF4: AJUDANTE DE MONTAGEM | DG4: VALOR R$ | DI4: SINALEIRO | DJ4: VALOR R$ | DL4: MONTADOR ANDAIME | DM4: VALOR R$ | DO4: PINTOR INDUSTRIAL | DP4: VALOR R$ | DR4: SOLDADOR CHAPARIA | DS4: VALOR R$ | DU4: OPERADOR EQUIPAMENTO PESADO | DV4: VALOR R$ | DX4: OPERADOR MUNCK | DY4: VALOR R$ | EA4: INSTRUMENTISTA | EB4: VALOR R$ | ED4: Bombeiro Hidráulico | EE4: VALOR R$ | EG4: JATISTA | EH4: VALOR R$ | EJ4: MOTORISTA DE CAMINHÃO | EK4: VALOR R$
B5: A) Salário mensal | C5: 17490 | E5: A) Salário mensal | F5: 14589 | H5: A) Salário mensal | I5: 14589 | K5: A) Salário mensal | L5: 14589 | N5: A) Salário mensal | O5: 8547.151 | Q5: A) Salário mensal | R5: 11111.296 | T5: A) Salário mensal | U5: 6916.8816 | W5: A) Salário mensal | X5: 5983.4668 | Z5: A) Salário mensal | AA5: 9595.5101 | AC5: A) Salário mensal | AD5: 6316.3174 | AF5: A) Salário mensal | AG5: 4808.16 | AI5: A) Salário mensal | AJ5: 2233.1868 | AL5: A) Salário mensal | AM5: 3987.8472 | AO5: A) Salário mensal | AP5: 4829.625 | AR5: A) Salário mensal | AS5: 2887.917 | AU5: A) Salário mensal | AV5: 2233.1868 | AX5: A) Salário mensal | AY5: 14481.72 | BA5: A) Salário mensal | BB5: 4910.76 | BD5: A) Salário mensal | BE5: 6327.5958 | BG5: A) Salário mensal | BH5: 5096.6496 | BJ5: A) Salário mensal | BK5: 4762.0924 | BM5: A) Salário mensal | BN5: 2360.2914 | BP5: A) Salário mensal | BQ5: 6013.4224 | BS5: A) Salário mensal | BT5: 2351.5464 | BV5: A) Salário mensal | BW5: 2779.2458 | BY5: A) Salário mensal | BZ5: 3860.0642 | CB5: A) Salário mensal | CC5: 5762.107 | CE5: A) Salário mensal | CF5: 4796.7491 | CH5: A) Salário mensal | CI5: 2586.4922 | CK5: A) Salário mensal | CL5: 3160.3688 | CN5: A) Salário mensal | CO5: 1783.98 | CQ5: A) Salário mensal | CR5: 4762.103 | CT5: A) Salário mensal | CU5: 5801.2316 | CW5: A) Salário mensal | CX5: 6411.2139 | CZ5: A) Salário mensal | DA5: 4078.3818 | DC5: A) Salário mensal | DD5: 6117.5727 | DF5: A) Salário mensal | DG5: 1830.2278 | DI5: A) Salário mensal | DJ5: 2252.9558 | DL5: A) Salário mensal | DM5: 3765.4804 | DO5: A) Salário mensal | DP5: 3600.5338 | DR5: A) Salário mensal | DS5: 4646.298 | DU5: A) Salário mensal | DV5: 4309.6314 | DX5: A) Salário mensal | DY5: 3931.9428 | EA5: A) Salário mensal | EB5: 6411.2139 | ED5: A) Salário mensal | EE5: 3066.4104 | EG5: A) Salário mensal | EH5: 3248.476 | EJ5: A) Salário mensal | EK5: 2901.1246
B6: Salário | C6: 17490 | E6: Salário | F6: 14589 | H6: Salário | I6: 14589 | K6: Salário | L6: 14589 | N6: Salário | O6: 8547.151 | Q6: Salário | R6: 8547.151 | T6: Salário | U6: 6916.8816 | W6: Salário | X6: 5983.4668 | Z6: Salário | AA6: 7381.1616 | AC6: Salário | AD6: 6316.3174 | AF6: Salário | AG6: 4808.16 | AI6: Salário | AJ6: 2233.1868 | AL6: Salário | AM6: 3987.8472 | AO6: Salário | AP6: 4829.625 | AR6: Salário | AS6: 2887.917 | AU6: Salário | AV6: 2233.1868 | AX6: Salário | AY6: 14481.72 | BA6: Salário | BB6: 4910.76 | BD6: Salário | BE6: 6327.5958 | BG6: Salário | BH6: 5096.6496 | BJ6: Salário | BK6: 4762.0924 | BM6: Salário | BN6: 2360.2914 | BP6: Salário | BQ6: 6013.4224 | BS6: Salário | BT6: 2351.5464 | BV6: Salário | BW6: 2779.2458 | BY6: Salário | BZ6: 3860.0642 | CB6: Salário | CC6: 4432.39 | CE6: Salário | CF6: 3689.807 | CH6: Salário | CI6: 1989.6094 | CK6: Salário | CL6: 3160.3688 | CN6: Salário | CO6: 1783.98 | CQ6: Salário | CR6: 4762.103 | CT6: Salário | CU6: 5801.2316 | CW6: Salário | CX6: 4931.703 | CZ6: Salário | DA6: 4078.3818 | DC6: Salário | DD6: 4078.3818 | DF6: Salário | DG6: 1830.2278 | DI6: Salário | DJ6: 2252.9558 | DL6: Salário | DM6: 3765.4804 | DO6: Salário | DP6: 3600.5338 | DR6: Salário | DS6: 4646.298 | DU6: Salário | DV6: 4309.6314 | DX6: Salário | DY6: 3931.9428 | EA6: Salário | EB6: 4931.703 | ED6: Salário | EE6: 3066.4104 | EG6: Salário | EH6: 3248.476 | EJ6: Salário | EK6: 2901.1246
B7: Insalubridade | C7: 0 | E7: Insalubridade | F7: 0 | H7: Insalubridade | I7: 0 | K7: Insalubridade | L7: 0 | N7: Insalubridade | O7: 0 | Q7: Insalubridade | R7: 0 | T7: Insalubridade | U7: 0 | W7: Insalubridade | X7: 0 | Z7: Insalubridade | AA7: 0 | AC7: Insalubridade | AD7: 0 | AF7: Insalubridade | AG7: 0 | AI7: Insalubridade | AJ7: 0 | AL7: Insalubridade | AM7: 0 | AO7: Insalubridade | AP7: 0 | AR7: Insalubridade | AS7: 0 | AU7: Insalubridade | AV7: 0 | AX7: Insalubridade | AY7: 0 | BA7: Insalubridade | BB7: 0 | BD7: Insalubridade | BE7: 0 | BG7: Insalubridade | BH7: 0 | BJ7: Insalubridade | BK7: 0 | BM7: Insalubridade | BN7: 0 | BP7: Insalubridade | BQ7: 0 | BS7: Insalubridade | BT7: 0 | BV7: Insalubridade | BW7: 0 | BY7: Insalubridade | BZ7: 0 | CB7: Insalubridade | CC7: 0 | CE7: Insalubridade | CF7: 0 | CH7: Insalubridade | CI7: 0 | CK7: Insalubridade | CL7: 0 | CN7: Insalubridade | CO7: 0 | CQ7: Insalubridade | CR7: 0 | CT7: Insalubridade | CU7: 0 | CW7: Insalubridade | CX7: 0 | CZ7: Insalubridade | DA7: 0 | DC7: Insalubridade | DD7: 815.67636 | DF7: Insalubridade | DG7: 0 | DI7: Insalubridade | DJ7: 0 | DL7: Insalubridade | DM7: 0 | DO7: Insalubridade | DP7: 0 | DR7: Insalubridade | DS7: 0 | DU7: Insalubridade | DV7: 0 | DX7: Insalubridade | DY7: 0 | EA7: Insalubridade | EB7: 0 | ED7: Insalubridade | EE7: 0 | EG7: Insalubridade | EH7: 0 | EJ7: Insalubridade | EK7: 0
B8: Periculosidade | C8: 0 | E8: Periculosidade | F8: 0 | H8: Periculosidade | I8: 0 | K8: Periculosidade | L8: 0 | N8: Periculosidade | O8: 0 | Q8: Periculosidade | R8: 2564.1453 | T8: Periculosidade | U8: 0 | W8: Periculosidade | X8: 0 | Z8: Periculosidade | AA8: 2214.3485 | AC8: Periculosidade | AD8: 0 | AF8: Periculosidade | AG8: 0 | AI8: Periculosidade | AJ8: 0 | AL8: Periculosidade | AM8: 0 | AO8: Periculosidade | AP8: 0 | AR8: Periculosidade | AS8: 0 | AU8: Periculosidade | AV8: 0 | AX8: Periculosidade | AY8: 0 | BA8: Periculosidade | BB8: 0 | BD8: Periculosidade | BE8: 0 | BG8: Periculosidade | BH8: 0 | BJ8: Periculosidade | BK8: 0 | BM8: Periculosidade | BN8: 0 | BP8: Periculosidade | BQ8: 0 | BS8: Periculosidade | BT8: 0 | BV8: Periculosidade | BW8: 0 | BY8: Periculosidade | BZ8: 0 | CB8: Periculosidade | CC8: 1329.717 | CE8: Periculosidade | CF8: 1106.9421 | CH8: Periculosidade | CI8: 596.88282 | CK8: Periculosidade | CL8: 0 | CN8: Periculosidade | CO8: 0 | CQ8: Periculosidade | CR8: 0 | CT8: Periculosidade | CU8: 0 | CW8: Periculosidade | CX8: 1479.5109 | CZ8: Periculosidade | DA8: 0 | DC8: Periculosidade | DD8: 1223.5145 | DF8: Periculosidade | DG8: 0 | DI8: Periculosidade | DJ8: 0 | DL8: Periculosidade | DM8: 0 | DO8: Periculosidade | DP8: 0 | DR8: Periculosidade | DS8: 0 | DU8: Periculosidade | DV8: 0 | DX8: Periculosidade | DY8: 0 | EA8: Periculosidade | EB8: 1479.5109 | ED8: Periculosidade | EE8: 0 | EG8: Periculosidade | EH8: 0 | EJ8: Periculosidade | EK8: 0
B9: Adicional Noturno | C9: 0 | E9: Adicional Noturno | F9: 0 | H9: Adicional Noturno | I9: 0 | K9: Adicional Noturno | L9: 0 | N9: Adicional Noturno | O9: 0 | Q9: Adicional Noturno | R9: 0 | T9: Adicional Noturno | U9: 0 | W9: Adicional Noturno | X9: 0 | Z9: Adicional Noturno | AA9: 0 | AC9: Adicional Noturno | AD9: 0 | AF9: Adicional Noturno | AG9: 0 | AI9: Adicional Noturno | AJ9: 0 | AL9: Adicional Noturno | AM9: 0 | AO9: Adicional Noturno | AP9: 0 | AR9: Adicional Noturno | AS9: 0 | AU9: Adicional Noturno | AV9: 0 | AX9: Adicional Noturno | AY9: 0 | BA9: Adicional Noturno | BB9: 0 | BD9: Adicional Noturno | BE9: 0 | BG9: Adicional Noturno | BH9: 0 | BJ9: Adicional Noturno | BK9: 0 | BM9: Adicional Noturno | BN9: 0 | BP9: Adicional Noturno | BQ9: 0 | BS9: Adicional Noturno | BT9: 0 | BV9: Adicional Noturno | BW9: 0 | BY9: Adicional Noturno | BZ9: 0 | CB9: Adicional Noturno | CC9: 0 | CE9: Adicional Noturno | CF9: 0 | CH9: Adicional Noturno | CI9: 0 | CK9: Adicional Noturno | CL9: 0 | CN9: Adicional Noturno | CO9: 0 | CQ9: Adicional Noturno | CR9: 0 | CT9: Adicional Noturno | CU9: 0 | CW9: Adicional Noturno | CX9: 0 | CZ9: Adicional Noturno | DA9: 0 | DC9: Adicional Noturno | DD9: 0 | DF9: Adicional Noturno | DG9: 0 | DI9: Adicional Noturno | DJ9: 0 | DL9: Adicional Noturno | DM9: 0 | DO9: Adicional Noturno | DP9: 0 | DR9: Adicional Noturno | DS9: 0 | DU9: Adicional Noturno | DV9: 0 | DX9: Adicional Noturno | DY9: 0 | EA9: Adicional Noturno | EB9: 0 | ED9: Adicional Noturno | EE9: 0 | EG9: Adicional Noturno | EH9: 0 | EJ9: Adicional Noturno | EK9: 0
B10: B) Encargos sociais | C10: 12711.749 | E10: B) Encargos sociais | F10: 10603.3 | H10: B) Encargos sociais | I10: 10603.3 | K10: B) Encargos sociais | L10: 10603.3 | N10: B) Encargos sociais | O10: 6212.0779 | Q10: B) Encargos sociais | R10: 8075.7013 | T10: B) Encargos sociais | U10: 5027.1965 | W10: B) Encargos sociais | X10: 4348.7897 | Z10: B) Encargos sociais | AA10: 6974.0263 | AC10: B) Encargos sociais | AD10: 4590.7058 | AF10: B) Encargos sociais | AG10: 3494.5755 | AI10: B) Encargos sociais | AJ10: 1623.0824 | AL10: B) Encargos sociais | AM10: 2898.3713 | AO10: B) Encargos sociais | AP10: 3510.1763 | AR10: B) Encargos sociais | AS10: 2098.941 | AU10: B) Encargos sociais | AV10: 1623.0824 | AX10: B) Encargos sociais | AY10: 10525.329 | BA10: B) Encargos sociais | BB10: 3569.1453 | BD10: B) Encargos sociais | BE10: 4598.903 | BG10: B) Encargos sociais | BH10: 3704.25 | BJ10: B) Encargos sociais | BK10: 3461.0935 | BM10: B) Encargos sociais | BN10: 1715.4621 | BP10: B) Encargos sociais | BQ10: 4370.5614 | BS10: B) Encargos sociais | BT10: 1709.1063 | BV10: B) Encargos sociais | BW10: 2019.9586 | BY10: B) Encargos sociais | BZ10: 2805.4985 | CB10: B) Encargos sociais | CC10: 4187.9051 | CE10: B) Encargos sociais | CF10: 3486.282 | CH10: B) Encargos sociais | CI10: 1879.8651 | CK10: B) Encargos sociais | CL10: 2296.9592 | CN10: B) Encargos sociais | CO10: 1296.5984 | CQ10: B) Encargos sociais | CR10: 3461.1012 | CT10: B) Encargos sociais | CU10: 4216.3409 | CW10: B) Encargos sociais | CX10: 4659.6767 | CZ10: B) Encargos sociais | DA10: 2964.172 | DC10: B) Encargos sociais | DD10: 4446.258 | DF10: B) Encargos sociais | DG10: 1330.2114 | DI10: B) Encargos sociais | DJ10: 1637.4505 | DL10: B) Encargos sociais | DM10: 2736.7549 | DO10: B) Encargos sociais | DP10: 2616.8716 | DR10: B) Encargos sociais | DS10: 3376.934 | DU10: B) Encargos sociais | DV10: 3132.2444 | DX10: B) Encargos sociais | DY10: 2857.74 | EA10: B) Encargos sociais | EB10: 4659.6767 | ED10: B) Encargos sociais | EE10: 2228.6701 | EG10: B) Encargos sociais | EH10: 2360.9956 | EJ10: B) Encargos sociais | EK10: 2108.5403
B11: C) Custos Diversos (soma c1+c2+c3+c4+c5+c6+c7) | C11: 2036.8117 | E11: C) Custos Diversos (soma c1+c2+c3+c4+c5+c6+c7) | F11: 2272.0117 | H11: C) Custos Diversos (soma c1+c2+c3+c4+c5+c6+c7) | I11: 2272.0117 | K11: C) Custos Diversos (soma c1+c2+c3+c4+c5+c6+c7) | L11: 2272.0117 | N11: C) Custos Diversos (soma c1+c2+c3+c4+c5+c6+c7) | O11: 4607.7083 | Q11: C) Custos Diversos (soma c1+c2+c3+c4+c5+c6+c7) | R11: 5305.4173 | T11: C) Custos Diversos (soma c1+c2+c3+c4+c5+c6+c7) | U11: 4164.1088 | W11: C) Custos Diversos (soma c1+c2+c3+c4+c5+c6+c7) | X11: 3910.1248 | Z11: C) Custos Diversos (soma c1+c2+c3+c4+c5+c6+c7) | AA11: 4938.3856 | AC11: C) Custos Diversos (soma c1+c2+c3+c4+c5+c6+c7) | AD11: 3990.6941 | AF11: C) Custos Diversos (soma c1+c2+c3+c4+c5+c6+c7) | AG11: 3580.3215 | AI11: C) Custos Diversos (soma c1+c2+c3+c4+c5+c6+c7) | AJ11: 2879.6662 | AL11: C) Custos Diversos (soma c1+c2+c3+c4+c5+c6+c7) | AM11: 3357.1128 | AO11: C) Custos Diversos (soma c1+c2+c3+c4+c5+c6+c7) | AP11: 3586.1622 | AR11: C) Custos Diversos (soma c1+c2+c3+c4+c5+c6+c7) | AS11: 3057.8196 | AU11: C) Custos Diversos (soma c1+c2+c3+c4+c5+c6+c7) | AV11: 2879.6662 | AX11: C) Custos Diversos (soma c1+c2+c3+c4+c5+c6+c7) | AY11: 2036.8117 | BA11: C) Custos Diversos (soma c1+c2+c3+c4+c5+c6+c7) | BB11: 2036.8117 | BD11: C) Custos Diversos (soma c1+c2+c3+c4+c5+c6+c7) | BE11: 3993.763 | BG11: C) Custos Diversos (soma c1+c2+c3+c4+c5+c6+c7) | BH11: 3658.8201 | BJ11: C) Custos Diversos (soma c1+c2+c3+c4+c5+c6+c7) | BK11: 3577.7864 | BM11: C) Custos Diversos (soma c1+c2+c3+c4+c5+c6+c7) | BN11: 2924.2516 | BP11: C) Custos Diversos (soma c1+c2+c3+c4+c5+c6+c7) | BQ11: 3918.2758 | BS11: C) Custos Diversos (soma c1+c2+c3+c4+c5+c6+c7) | BT11: 2921.8721 | BV11: C) Custos Diversos (soma c1+c2+c3+c4+c5+c6+c7) | BW11: 3038.2499 | BY11: C) Custos Diversos (soma c1+c2+c3+c4+c5+c6+c7) | BZ11: 3332.3428 | CB11: C) Custos Diversos (soma c1+c2+c3+c4+c5+c6+c7) | CC11: 4015.4507 | CE11: C) Custos Diversos (soma c1+c2+c3+c4+c5+c6+c7) | CF11: 3752.7749 | CH11: C) Custos Diversos (soma c1+c2+c3+c4+c5+c6+c7) | CI11: 3151.3596 | CK11: C) Custos Diversos (soma c1+c2+c3+c4+c5+c6+c7) | CL11: 3225.1793 | CN11: C) Custos Diversos (soma c1+c2+c3+c4+c5+c6+c7) | CO11: 2850.6611 | CQ11: C) Custos Diversos (soma c1+c2+c3+c4+c5+c6+c7) | CR11: 3661.0143 | CT11: C) Custos Diversos (soma c1+c2+c3+c4+c5+c6+c7) | CU11: 4071.0132 | CW11: C) Custos Diversos (soma c1+c2+c3+c4+c5+c6+c7) | CX11: 4192.074 | CZ11: C) Custos Diversos (soma c1+c2+c3+c4+c5+c6+c7) | DA11: 3445.6391 | DC11: C) Custos Diversos (soma c1+c2+c3+c4+c5+c6+c7) | DD11: 4000.507 | DF11: C) Custos Diversos (soma c1+c2+c3+c4+c5+c6+c7) | DG11: 2833.9119 | DI11: C) Custos Diversos (soma c1+c2+c3+c4+c5+c6+c7) | DJ11: 2978.2704 | DL11: C) Custos Diversos (soma c1+c2+c3+c4+c5+c6+c7) | DM11: 3360.498 | DO11: C) Custos Diversos (soma c1+c2+c3+c4+c5+c6+c7) | DP11: 3344.949 | DR11: C) Custos Diversos (soma c1+c2+c3+c4+c5+c6+c7) | DS11: 3756.7535 | DU11: C) Custos Diversos (soma c1+c2+c3+c4+c5+c6+c7) | DV11: 3478.3126 | DX11: C) Custos Diversos (soma c1+c2+c3+c4+c5+c6+c7) | DY11: 3375.5427 | EA11: C) Custos Diversos (soma c1+c2+c3+c4+c5+c6+c7) | EB11: 2447.57 | ED11: C) Custos Diversos (soma c1+c2+c3+c4+c5+c6+c7) | EE11: 3199.613 | EG11: C) Custos Diversos (soma c1+c2+c3+c4+c5+c6+c7) | EH11: 3249.1534 | EJ11: C) Custos Diversos (soma c1+c2+c3+c4+c5+c6+c7) | EK11: 3154.6384
B12: C1) Alimentação | C12: 0 | E12: C1) Alimentação | F12: 0 | H12: C1) Alimentação | I12: 0 | K12: C1) Alimentação | L12: 0 | N12: C1) Alimentação | O12: 0 | Q12: C1) Alimentação | R12: 0 | T12: C1) Alimentação | U12: 0 | W12: C1) Alimentação | X12: 0 | Z12: C1) Alimentação | AA12: 0 | AC12: C1) Alimentação | AD12: 0 | AF12: C1) Alimentação | AG12: 0 | AI12: C1) Alimentação | AJ12: 0 | AL12: C1) Alimentação | AM12: 0 | AO12: C1) Alimentação | AP12: 0 | AR12: C1) Alimentação | AS12: 0 | AU12: C1) Alimentação | AV12: 0 | AX12: C1) Alimentação | AY12: 0 | BA12: C1) Alimentação | BB12: 0 | BD12: C1) Alimentação | BE12: 0 | BG12: C1) Alimentação | BH12: 0 | BJ12: C1) Alimentação | BK12: 0 | BM12: C1) Alimentação | BN12: 0 | BP12: C1) Alimentação | BQ12: 0 | BS12: C1) Alimentação | BT12: 0 | BV12: C1) Alimentação | BW12: 0 | BY12: C1) Alimentação | BZ12: 0 | CB12: C1) Alimentação | CC12: 0 | CE12: C1) Alimentação | CF12: 0 | CH12: C1) Alimentação | CI12: 0 | CK12: C1) Alimentação | CL12: 0 | CN12: C1) Alimentação | CO12: 0 | CQ12: C1) Alimentação | CR12: 0 | CT12: C1) Alimentação | CU12: 0 | CW12: C1) Alimentação | CX12: 0 | CZ12: C1) Alimentação | DA12: 0 | DC12: C1) Alimentação | DD12: 0 | DF12: C1) Alimentação | DG12: 0 | DI12: C1) Alimentação | DJ12: 0 | DL12: C1) Alimentação | DM12: 0 | DO12: C1) Alimentação | DP12: 0 | DR12: C1) Alimentação | DS12: 0 | DU12: C1) Alimentação | DV12: 0 | DX12: C1) Alimentação | DY12: 0 | EA12: C1) Alimentação | EB12: 0 | ED12: C1) Alimentação | EE12: 0 | EG12: C1) Alimentação | EH12: 0 | EJ12: C1) Alimentação | EK12: 0
B13: DESJEJUM | C13: 0 | E13: DESJEJUM | F13: 0 | H13: DESJEJUM | I13: 0 | K13: DESJEJUM | L13: 0 | N13: DESJEJUM | O13: 0 | Q13: DESJEJUM | R13: 0 | T13: DESJEJUM | U13: 0 | W13: DESJEJUM | X13: 0 | Z13: DESJEJUM | AA13: 0 | AC13: DESJEJUM | AD13: 0 | AF13: DESJEJUM | AG13: 0 | AI13: DESJEJUM | AJ13: 0 | AL13: DESJEJUM | AM13: 0 | AO13: DESJEJUM | AP13: 0 | AR13: DESJEJUM | AS13: 0 | AU13: DESJEJUM | AV13: 0 | AX13: DESJEJUM | AY13: 0 | BA13: DESJEJUM | BB13: 0 | BD13: DESJEJUM | BE13: 0 | BG13: DESJEJUM | BH13: 0 | BJ13: DESJEJUM | BK13: 0 | BM13: DESJEJUM | BN13: 0 | BP13: DESJEJUM | BQ13: 0 | BS13: DESJEJUM | BT13: 0 | BV13: DESJEJUM | BW13: 0 | BY13: DESJEJUM | BZ13: 0 | CB13: DESJEJUM | CC13: 0 | CE13: DESJEJUM | CF13: 0 | CH13: DESJEJUM | CI13: 0 | CK13: DESJEJUM | CL13: 0 | CN13: DESJEJUM | CO13: 0 | CQ13: DESJEJUM | CR13: 0 | CT13: DESJEJUM | CU13: 0 | CW13: DESJEJUM | CX13: 0 | CZ13: DESJEJUM | DA13: 0 | DC13: DESJEJUM | DD13: 0 | DF13: DESJEJUM | DG13: 0 | DI13: DESJEJUM | DJ13: 0 | DL13: DESJEJUM | DM13: 0 | DO13: DESJEJUM | DP13: 0 | DR13: DESJEJUM | DS13: 0 | DU13: DESJEJUM | DV13: 0 | DX13: DESJEJUM | DY13: 0 | EA13: DESJEJUM | EB13: 0 | ED13: DESJEJUM | EE13: 0 | EG13: DESJEJUM | EH13: 0 | EJ13: DESJEJUM | EK13: 0
B14: C2) Transporte | C14: 0 | E14: C2) Transporte | F14: 235.2 | H14: C2) Transporte | I14: 235.2 | K14: C2) Transporte | L14: 235.2 | N14: C2) Transporte | O14: 235.2 | Q14: C2) Transporte | R14: 235.2 | T14: C2) Transporte | U14: 235.2 | W14: C2) Transporte | X14: 235.2 | Z14: C2) Transporte | AA14: 235.2 | AC14: C2) Transporte | AD14: 235.2 | AF14: C2) Transporte | AG14: 235.2 | AI14: C2) Transporte | AJ14: 235.2 | AL14: C2) Transporte | AM14: 235.2 | AO14: C2) Transporte | AP14: 235.2 | AR14: C2) Transporte | AS14: 235.2 | AU14: C2) Transporte | AV14: 235.2 | AX14: C2) Transporte | AY14: 0 | BA14: C2) Transporte | BB14: 0 | BD14: C2) Transporte | BE14: 235.2 | BG14: C2) Transporte | BH14: 235.2 | BJ14: C2) Transporte | BK14: 235.2 | BM14: C2) Transporte | BN14: 235.2 | BP14: C2) Transporte | BQ14: 235.2 | BS14: C2) Transporte | BT14: 235.2 | BV14: C2) Transporte | BW14: 235.2 | BY14: C2) Transporte | BZ14: 235.2 | CB14: C2) Transporte | CC14: 235.2 | CE14: C2) Transporte | CF14: 235.2 | CH14: C2) Transporte | CI14: 235.2 | CK14: C2) Transporte | CL14: 235.2 | CN14: C2) Transporte | CO14: 235.2 | CQ14: C2) Transporte | CR14: 235.2 | CT14: C2) Transporte | CU14: 235.2 | CW14: C2) Transporte | CX14: 235.2 | CZ14: C2) Transporte | DA14: 235.2 | DC14: C2) Transporte | DD14: 235.2 | DF14: C2) Transporte | DG14: 235.2 | DI14: C2) Transporte | DJ14: 235.2 | DL14: C2) Transporte | DM14: 235.2 | DO14: C2) Transporte | DP14: 235.2 | DR14: C2) Transporte | DS14: 235.2 | DU14: C2) Transporte | DV14: 235.2 | DX14: C2) Transporte | DY14: 235.2 | EA14: C2) Transporte | EB14: 235.2 | ED14: C2) Transporte | EE14: 235.2 | EG14: C2) Transporte | EH14: 235.2 | EJ14: C2) Transporte | EK14: 235.2
B15: Ônibus transporte externo - vale transporte | C15: 235.2 | E15: Ônibus transporte externo - vale transporte | F15: 235.2 | H15: Ônibus transporte externo - vale transporte | I15: 235.2 | K15: Ônibus transporte externo - vale transporte | L15: 235.2 | N15: Ônibus transporte externo - vale transporte | O15: 235.2 | Q15: Ônibus transporte externo - vale transporte | R15: 235.2 | T15: Ônibus transporte externo - vale transporte | U15: 235.2 | W15: Ônibus transporte externo - vale transporte | X15: 235.2 | Z15: Ônibus transporte externo - vale transporte | AA15: 235.2 | AC15: Ônibus transporte externo - vale transporte | AD15: 235.2 | AF15: Ônibus transporte externo - vale transporte | AG15: 235.2 | AI15: Ônibus transporte externo - vale transporte | AJ15: 235.2 | AL15: Ônibus transporte externo - vale transporte | AM15: 235.2 | AO15: Ônibus transporte externo - vale transporte | AP15: 235.2 | AR15: Ônibus transporte externo - vale transporte | AS15: 235.2 | AU15: Ônibus transporte externo - vale transporte | AV15: 235.2 | AX15: Ônibus transporte externo - vale transporte | AY15: 235.2 | BA15: Ônibus transporte externo - vale transporte | BB15: 235.2 | BD15: Ônibus transporte externo - vale transporte | BE15: 235.2 | BG15: Ônibus transporte externo - vale transporte | BH15: 235.2 | BJ15: Ônibus transporte externo - vale transporte | BK15: 235.2 | BM15: Ônibus transporte externo - vale transporte | BN15: 235.2 | BP15: Ônibus transporte externo - vale transporte | BQ15: 235.2 | BS15: Ônibus transporte externo - vale transporte | BT15: 235.2 | BV15: Ônibus transporte externo - vale transporte | BW15: 235.2 | BY15: Ônibus transporte externo - vale transporte | BZ15: 235.2 | CB15: Ônibus transporte externo - vale transporte | CC15: 235.2 | CE15: Ônibus transporte externo - vale transporte | CF15: 235.2 | CH15: Ônibus transporte externo - vale transporte | CI15: 235.2 | CK15: Ônibus transporte externo - vale transporte | CL15: 235.2 | CN15: Ônibus transporte externo - vale transporte | CO15: 235.2 | CQ15: Ônibus transporte externo - vale transporte | CR15: 235.2 | CT15: Ônibus transporte externo - vale transporte | CU15: 235.2 | CW15: Ônibus transporte externo - vale transporte | CX15: 235.2 | CZ15: Ônibus transporte externo - vale transporte | DA15: 235.2 | DC15: Ônibus transporte externo - vale transporte | DD15: 235.2 | DF15: Ônibus transporte externo - vale transporte | DG15: 235.2 | DI15: Ônibus transporte externo - vale transporte | DJ15: 235.2 | DL15: Ônibus transporte externo - vale transporte | DM15: 235.2 | DO15: Ônibus transporte externo - vale transporte | DP15: 235.2 | DR15: Ônibus transporte externo - vale transporte | DS15: 235.2 | DU15: Ônibus transporte externo - vale transporte | DV15: 235.2 | DX15: Ônibus transporte externo - vale transporte | DY15: 235.2 | EA15: Ônibus transporte externo - vale transporte | EB15: 235.2 | ED15: Ônibus transporte externo - vale transporte | EE15: 235.2 | EG15: Ônibus transporte externo - vale transporte | EH15: 235.2 | EJ15: Ônibus transporte externo - vale transporte | EK15: 235.2
B16: C3) Uniforme | C16: 30 | E16: C3) Uniforme | F16: 30 | H16: C3) Uniforme | I16: 30 | K16: C3) Uniforme | L16: 30 | N16: C3) Uniforme | O16: 40 | Q16: C3) Uniforme | R16: 40 | T16: C3) Uniforme | U16: 40 | W16: C3) Uniforme | X16: 40 | Z16: C3) Uniforme | AA16: 85.416667 | AC16: C3) Uniforme | AD16: 30 | AF16: C3) Uniforme | AG16: 30 | AI16: C3) Uniforme | AJ16: 30 | AL16: C3) Uniforme | AM16: 30 | AO16: C3) Uniforme | AP16: 30 | AR16: C3) Uniforme | AS16: 30 | AU16: C3) Uniforme | AV16: 30 | AX16: C3) Uniforme | AY16: 30 | BA16: C3) Uniforme | BB16: 30 | BD16: C3) Uniforme | BE16: 30 | BG16: C3) Uniforme | BH16: 30 | BJ16: C3) Uniforme | BK16: 40 | BM16: C3) Uniforme | BN16: 40 | BP16: C3) Uniforme | BQ16: 40 | BS16: C3) Uniforme | BT16: 40 | BV16: C3) Uniforme | BW16: 40 | BY16: C3) Uniforme | BZ16: 40 | CB16: C3) Uniforme | CC16: 85.416667 | CE16: C3) Uniforme | CF16: 85.416667 | CH16: C3) Uniforme | CI16: 85.416667 | CK16: C3) Uniforme | CL16: 40 | CN16: C3) Uniforme | CO16: 40 | CQ16: C3) Uniforme | CR16: 40 | CT16: C3) Uniforme | CU16: 40 | CW16: C3) Uniforme | CX16: 85.416667 | CZ16: C3) Uniforme | DA16: 40 | DC16: C3) Uniforme | DD16: 40 | DF16: C3) Uniforme | DG16: 40 | DI16: C3) Uniforme | DJ16: 40 | DL16: C3) Uniforme | DM16: 40 | DO16: C3) Uniforme | DP16: 40 | DR16: C3) Uniforme | DS16: 40 | DU16: C3) Uniforme | DV16: 40 | DX16: C3) Uniforme | DY16: 40 | EA16: C3) Uniforme | EB16: 85.416667 | ED16: C3) Uniforme | EE16: 40 | EG16: C3) Uniforme | EH16: 40 | EJ16: C3) Uniforme | EK16: 40
... B34: Nº de horas Trabalhadas no mês (x) | C34: 176 | E34: Nº de horas Trabalhadas no mês (x) | F34: 176 | H34: Nº de horas Trabalhadas no mês (x) | I34: 176 | K34: Nº de horas Trabalhadas no mês (x) | L34: 176 | N34: Nº de horas Trabalhadas no mês (x) | O34: 176 | Q34: Nº de horas Trabalhadas no mês (x) | R34: 176 | T34: Nº de horas Trabalhadas no mês (x) | U34: 176 | W34: Nº de horas Trabalhadas no mês (x) | X34: 176 | Z34: Nº de horas Trabalhadas no mês (x) | AA34: 176 | AC34: Nº de horas Trabalhadas no mês (x) | AD34: 176 | AF34: Nº de horas Trabalhadas no mês (x) | AG34: 176 | AI34: Nº de horas Trabalhadas no mês (x) | AJ34: 176 | AL34: Nº de horas Trabalhadas no mês (x) | AM34: 176 | AO34: Nº de horas Trabalhadas no mês (x) | AP34: 176 | AR34: Nº de horas Trabalhadas no mês (x) | AS34: 176 | AU34: Nº de horas Trabalhadas no mês (x) | AV34: 176 | AX34: Nº de horas Trabalhadas no mês (x) | AY34: 176 | BA34: Nº de horas Trabalhadas no mês (x) | BB34: 176 | BD34: Nº de horas Trabalhadas no mês (x) | BE34: 176 | BG34: Nº de horas Trabalhadas no mês (x) | BH34: 176 | BJ34: Nº de horas Trabalhadas no mês (x) | BK34: 176 | BM34: Nº de horas Trabalhadas no mês (x) | BN34: 176 | BP34: Nº de horas Trabalhadas no mês (x) | BQ34: 176 | BS34: Nº de horas Trabalhadas no mês (x) | BT34: 176 | BV34: Nº de horas Trabalhadas no mês (x) | BW34: 176 | BY34: Nº de horas Trabalhadas no mês (x) | BZ34: 176 | CB34: Nº de horas Trabalhadas no mês (x) | CC34: 132 | CE34: Nº de horas Trabalhadas no mês (x) | CF34: 132 | CH34: Nº de horas Trabalhadas no mês (x) | CI34: 132 | CK34: Nº de horas Trabalhadas no mês (x) | CL34: 132 | CN34: Nº de horas Trabalhadas no mês (x) | CO34: 132 | CQ34: Nº de horas Trabalhadas no mês (x) | CR34: 132 | CT34: Nº de horas Trabalhadas no mês (x) | CU34: 132 | CW34: Nº de horas Trabalhadas no mês (x) | CX34: 132 | CZ34: Nº de horas Trabalhadas no mês (x) | DA34: 132 | DC34: Nº de horas Trabalhadas no mês (x) | DD34: 132 | DF34: Nº de horas Trabalhadas no mês (x) | DG34: 132 | DI34: Nº de horas Trabalhadas no mês (x) | DJ34: 132 | DL34: Nº de horas Trabalhadas no mês (x) | DM34: 132 | DO34: Nº de horas Trabalhadas no mês (x) | DP34: 132 | DR34: Nº de horas Trabalhadas no mês (x) | DS34: 132 | DU34: Nº de horas Trabalhadas no mês (x) | DV34: 132 | DX34: Nº de horas Trabalhadas no mês (x) | DY34: 132 | EA34: Nº de horas Trabalhadas no mês (x) | EB34: 132 | ED34: Nº de horas Trabalhadas no mês (x) | EE34: 132 | EG34: Nº de horas Trabalhadas no mês (x) | EH34: 132 | EJ34: Nº de horas Trabalhadas no mês (x) | EK34: 132
B36: CÁLCULO DO CUSTO DO HOMEM | E36: CÁLCULO DO CUSTO DO HOMEM | H36: CÁLCULO DO CUSTO DO HOMEM | K36: CÁLCULO DO CUSTO DO HOMEM | N36: CÁLCULO DO CUSTO DO HOMEM | Q36: CÁLCULO DO CUSTO DO HOMEM | T36: CÁLCULO DO CUSTO DO HOMEM | W36: CÁLCULO DO CUSTO DO HOMEM | Z36: CÁLCULO DO CUSTO DO HOMEM | AC36: CÁLCULO DO CUSTO DO HOMEM | AF36: CÁLCULO DO CUSTO DO HOMEM | AI36: CÁLCULO DO CUSTO DO HOMEM | AL36: CÁLCULO DO CUSTO DO HOMEM | AO36: CÁLCULO DO CUSTO DO HOMEM | AR36: CÁLCULO DO CUSTO DO HOMEM | AU36: CÁLCULO DO CUSTO DO HOMEM | AX36: CÁLCULO DO CUSTO DO HOMEM | BA36: CÁLCULO DO CUSTO DO HOMEM | BD36: CÁLCULO DO CUSTO DO HOMEM | BG36: CÁLCULO DO CUSTO DO HOMEM | BJ36: CÁLCULO DO CUSTO DO HOMEM | BM36: CÁLCULO DO CUSTO DO HOMEM | BP36: CÁLCULO DO CUSTO DO HOMEM | BS36: CÁLCULO DO CUSTO DO HOMEM | BV36: CÁLCULO DO CUSTO DO HOMEM | BY36: CÁLCULO DO CUSTO DO HOMEM | CB36: CÁLCULO DO CUSTO DO HOMEM | CE36: CÁLCULO DO CUSTO DO HOMEM | CH36: CÁLCULO DO CUSTO DO HOMEM | CK36: CÁLCULO DO CUSTO DO HOMEM | CN36: CÁLCULO DO CUSTO DO HOMEM | CQ36: CÁLCULO DO CUSTO DO HOMEM | CT36: CÁLCULO DO CUSTO DO HOMEM | CW36: CÁLCULO DO CUSTO DO HOMEM | CZ36: CÁLCULO DO CUSTO DO HOMEM | DC36: CÁLCULO DO CUSTO DO HOMEM | DF36: CÁLCULO DO CUSTO DO HOMEM | DI36: CÁLCULO DO CUSTO DO HOMEM | DL36: CÁLCULO DO CUSTO DO HOMEM | DO36: CÁLCULO DO CUSTO DO HOMEM | DR36: CÁLCULO DO CUSTO DO HOMEM | DU36: CÁLCULO DO CUSTO DO HOMEM | DX36: CÁLCULO DO CUSTO DO HOMEM | EA36: CÁLCULO DO CUSTO DO HOMEM | ED36: CÁLCULO DO CUSTO DO HOMEM | EG36: CÁLCULO DO CUSTO DO HOMEM | EJ36: CÁLCULO DO CUSTO DO HOMEM
B37: Custo homem hora sem BDI (a+b+c)/x | C37: 183.17364 | E37: Custo homem hora sem BDI (a+b+c)/x | F37: 156.04722 | H37: Custo homem hora sem BDI (D/G) | I37: 156.04722 | K37: Custo homem hora sem BDI (a+b+c)/x | L37: 156.04722 | N37: Custo homem hora sem BDI (D/G) | O37: 110.03942 | Q37: Custo homem hora sem BDI (D/G) | R37: 139.16145 | T37: Custo homem hora sem BDI (D/G) | U37: 91.523789 | W37: Custo homem hora sem BDI (D/G) | X37: 80.922621 | Z37: Custo homem hora sem BDI (D/G) | AA37: 122.2041 | AC37: Custo homem hora sem BDI (a+b+c)/x | AD37: 84.646121 | AF37: Custo homem hora sem BDI (a+b+c)/x | AG37: 67.517369 | AI37: Custo homem hora sem BDI (a+b+c)/x | AJ37: 38.27236 | AL37: Custo homem hora sem BDI (D/G) | AM37: 58.200746 | AO37: Custo homem hora sem BDI (D/G) | AP37: 67.761156 | AR37: Custo homem hora sem BDI (D/G) | AS37: 45.708395 | AU37: Custo homem hora sem BDI (D/G) | AV37: 38.27236 | AX37: Custo homem hora sem BDI (a+b+c)/x | AY37: 153.6583 | BA37: Custo homem hora sem BDI (a+b+c)/x | BB37: 59.754074 | BD37: Custo homem hora sem BDI (D/G) | BE37: 84.774214 | BG37: Custo homem hora sem BDI (D/G) | BH37: 70.793862 | BJ37: Custo homem hora sem BDI (D/G) | BK37: 67.050979 | BM37: Custo homem hora sem BDI (D/G) | BN37: 39.772757 | BP37: Custo homem hora sem BDI (D/G) | BQ37: 81.262839 | BS37: Custo homem hora sem BDI (D/G) | BT37: 39.673436 | BV37: Custo homem hora sem BDI (D/G) | BW37: 44.530991 | BY37: Custo homem hora sem BDI (D/G) | BZ37: 56.806281 | CB37: Custo homem hora sem BDI (D/G) | CC37: 105.79896 | CE37: Custo homem hora sem BDI (D/G) | CF37: 91.180349 | CH37: Custo homem hora sem BDI (D/G) | CI37: 57.709977 | CK37: Custo homem hora sem BDI (D/G) | CL37: 65.77657 | CN37: Custo homem hora sem BDI (D/G) | CO37: 44.933633 | CQ37: Custo homem hora sem BDI (D/G) | CR37: 90.031959 | CT37: Custo homem hora sem BDI (D/G) | CU37: 106.73171 | CW37: Custo homem hora sem BDI (D/G) | CX37: 115.62852 | CZ37: Custo homem hora sem BDI (D/G) | DA37: 79.456006 | DC37: Custo homem hora sem BDI (D/G) | DD37: 110.33589 | DF37: Custo homem hora sem BDI (D/G) | DG37: 45.411751 | DI37: Custo homem hora sem BDI (D/G) | DJ37: 52.03543 | DL37: Custo homem hora sem BDI (D/G) | DM37: 74.717677 | DO37: Custo homem hora sem BDI (D/G) | DP37: 72.442079 | DR37: Custo homem hora sem BDI (D/G) | DS37: 89.242315 | DU37: Custo homem hora sem BDI (D/G) | DV37: 82.7287 | DX37: Custo homem hora sem BDI (D/G) | DY37: 77.009284 | EA37: Custo homem hora sem BDI (D/G) | EB37: 102.41258 | ED37: Custo homem hora sem BDI (D/G) | EE37: 64.353739 | EG37: Custo homem hora sem BDI (D/G) | EH37: 67.110796 | EJ37: Custo homem hora sem BDI (D/G) | EK37: 61.850782
B38: Custo Homem Hora com BDI (a+b+c+d)/x | C38: 228.29873 | E38: Custo Homem Hora com BDI (a+b+c+d)/x | F38: 194.48968 | H38: Custo Homem Hora com BDI (F/G) | I38: 194.48968 | K38: Custo Homem Hora com BDI (a+b+c+d)/x | L38: 194.48968 | N38: Custo Homem Hora com BDI (F/G) | O38: 137.14778 | Q38: Custo Homem Hora com BDI (F/G) | R38: 173.44407 | T38: Custo Homem Hora com BDI (F/G) | U38: 114.07081 | W38: Custo Homem Hora com BDI (F/G) | X38: 100.85802 | Z38: Custo Homem Hora com BDI (F/G) | AA38: 152.30926 | AC38: Custo Homem Hora com BDI (a+b+c+d)/x | AD38: 105.49881 | AF38: Custo Homem Hora com BDI (a+b+c+d)/x | AG38: 84.15037 | AI38: Custo Homem Hora com BDI (a+b+c+d)/x | AJ38: 47.700811 | AL38: Custo Homem Hora com BDI (F/G) | AM38: 72.538583 | AO38: Custo Homem Hora com BDI (F/G) | AP38: 84.454214 | AR38: Custo Homem Hora com BDI (F/G) | AS38: 56.968724 | AU38: Custo Homem Hora com BDI (F/G) | AV38: 47.700811 | AX38: Custo Homem Hora com BDI (a+b+c+d)/x | AY38: 191.51224 | BA38: Custo Homem Hora com BDI (a+b+c+d)/x | BB38: 74.474575 | BD38: Custo Homem Hora com BDI (F/G) | BE38: 105.65846 | BG38: Custo Homem Hora com BDI (F/G) | BH38: 88.234031 | BJ38: Custo Homem Hora com BDI (F/G) | BK38: 83.569084 | BM38: Custo Homem Hora com BDI (F/G) | BN38: 49.570832 | BP38: Custo Homem Hora com BDI (F/G) | BQ38: 101.28206 | BS38: Custo Homem Hora com BDI (F/G) | BT38: 49.447044 | BV38: Custo Homem Hora com BDI (F/G) | BW38: 55.501264 | BY38: Custo Homem Hora com BDI (F/G) | BZ38: 70.80059 | CB38: Custo Homem Hora com BDI (F/G) | CC38: 131.86269 | CE38: Custo Homem Hora com BDI (F/G) | CF38: 113.64276 | CH38: Custo Homem Hora com BDI (F/G) | CI38: 71.926913 | CK38: Custo Homem Hora com BDI (F/G) | CL38: 81.980722 | CN38: Custo Homem Hora com BDI (F/G) | CO38: 56.003098 | CQ38: Custo Homem Hora com BDI (F/G) | CR38: 112.21146 | CT38: Custo Homem Hora com BDI (F/G) | CU38: 133.02522 | CW38: Custo Homem Hora com BDI (F/G) | CX38: 144.11377 | CZ38: Custo Homem Hora com BDI (F/G) | DA38: 99.030107 | DC38: Custo Homem Hora com BDI (F/G) | DD38: 137.5173 | DF38: Custo Homem Hora com BDI (F/G) | DG38: 56.599001 | DI38: Custo Homem Hora com BDI (F/G) | DJ38: 64.854432 | DL38: Custo Homem Hora com BDI (F/G) | DM38: 93.124483 | DO38: Custo Homem Hora com BDI (F/G) | DP38: 90.288288 | DR38: Custo Homem Hora com BDI (F/G) | DS38: 111.22729 | DU38: Custo Homem Hora com BDI (F/G) | DV38: 103.10903 | DX38: Custo Homem Hora com BDI (F/G) | DY38: 95.980631 | EA38: Custo Homem Hora com BDI (F/G) | EB38: 127.64207 | ED38: Custo Homem Hora com BDI (F/G) | EE38: 80.207375 | EG38: Custo Homem Hora com BDI (F/G) | EH38: 83.643636 | EJ38: Custo Homem Hora com BDI (F/G) | EK38: 77.087811

Sheet Equip
B3: COMPOSIÇÃO DE CUSTO EQUIPAMENTOS
B5: Resumo | C5: Valor | D5: Unidade
B6: Retroescavadeira com combustível e Operador | C6: 266.97112 | D6: h
B7: Caminhão basculante com combustível e motorista | C7: 133.24472 | D7: h
B8: Caminhão Munck com combustível e operador | C8: 264.06231 | D8: h
B9: Plataforma elevatória 600AJ | C9: 198.0303 | D9: h
B10: Plataforma elevatória 800AJ | C10: 253.93939 | D10: h
B11: Equipamento perfuração de estaca Helice Contínua - diária - 600mm a 800mm | C11: 15000 | D11: dia
B12: Equipamento perfuração de estaca raíz - diária - 400mm | C12: 10000 | D12: dia
B13: Escavadeira com combustível e Operador | C13: 429.21355 | D13: h
B14: Escavadeira hidraulica com rompedor | C14: 506.42567 | D14: h
B15: Caminhão pipa com operador | C15: 183.85078 | D15: h
B16: Rolo compactador | C16: 187.63636 | D16: h
B17: Trator com grade | C17: 208.54545 | D17: h
... B23: GUINDASTE 440TON | C23: 1661.5904 | D23: h
B24: CAMINHÃO BASCULANTE 12M3
B25: LOCAÇÃO | C25: H X Comb. | D25: 96 | E25: Efetivo | F25: 132
B26: CAMINHÃO BASCULANTE | C26: Unid | D26: QTD. | E26: LOCAÇÃO | F26: TOTAL | G26: CUSTO HORÁRIO HN
B27: Locação Mensal | C27: mês | D27: 1 | E27: 20000 | F27: 2000 | G27: 15.151515
B28: Hora extra mensal | C28: hh | E28: 100 | F28: 0 | G28: 0
B29: Manutenção | C29: mês | D29: 1 | E29: 800 | F29: 800 | G29: 6.0606061
B30: Operador de Equipamento | C30: mês | D30: 1 | E30: 8164.3033 | F30: 8164.3033 | G30: 61.850782
B31: Diesel | C31: L | D31: 1584 | E31: 5.75 | F31: 6624 | G31: 50.181818
B32: CUSTO TOTAL DE LOCAÇÃO DE EQUIPAMENTOS | F32: 17588.303 | G32: 133.24472
B34: MOTONIVELADORA
B35: LOCAÇÃO | C35: H X Comb. | D35: 96 | E35: Efetivo | F35: 132
B36: MOTONIVELADORA | D36: QTD. | E36: LOCAÇÃO | F36: TOTAL | G36: CUSTO HORÁRIO
B37: Locação Mensal | C37: mês | D37: 1 | E37: 30000 | F37: 30000 | G37: 227.27273
B38: Hora extra mensal | C38: hh | D38: 0 | E38: 150 | F38: 0 | G38: 0
B39: Mobilização | C39: unid | D39: 1 | F39: 0 | G39: 0
B40: Manutenção | C40: mês | D40: 1 | E40: 800 | F40: 800 | G40: 6.0606061
B41: Operador de Equipamento | C41: mês | D41: 1 | E41: 10920.188 | F41: 10920.188 | G41: 82.7287
B42: Diesel | C42: L | D42: 1848 | E42: 5.75 | F42: 7728 | G42: 58.545455
B43: CUSTO TOTAL DE LOCAÇÃO DE EQUIPAMENTOS | F43: 49448.188 | G43: 374.60749
B45: PÁ CARREGADEIRA
B46: LOCAÇÃO | C46: H X Comb. | D46: 96 | E46: Efetivo | F46: 132
B47: PÁ CARREGADEIRA | D47: QTD. | E47: LOCAÇÃO | F47: TOTAL | G47: CUSTO HORÁRIO
B48: Locação Mensal | C48: mês | D48: 1 | E48: 26000 | F48: 26000 | G48: 196.9697
B49: Hora extra mensal | C49: hh | D49: 0 | E49: 130 | F49: 0 | G49: 0
B50: Mobilização | C50: unid | D50: 1 | F50: 0 | G50: 0
B51: Manutenção | C51: mês | D51: 1 | E51: 800 | F51: 800 | G51: 6.0606061
B52: Operador de Equipamento | C52: mês | D52: 1 | E52: 0 | F52: 0 | G52: 0
B53: Diesel | C53: L | D53: 1848 | E53: 5.75 | F53: 7728 | G53: 58.545455
B54: CUSTO TOTAL DE LOCAÇÃO DE EQUIPAMENTOS | F54: 34528 | G54: 261.57576
B56: ROLO CORRUGADO
B57: LOCAÇÃO | C57: H X Comb. | D57: 96 | E57: Efetivo | F57: 132
B58: ROLO CORRUGADO | D58: QTD. | E58: LOCAÇÃO | F58: TOTAL | G58: CUSTO HORÁRIO
B59: Locação Mensal | C59: mês | D59: 1 | E59: 19000 | F59: 19000 | G59: 143.93939
B60: Hora extra mensal | C60: hh | D60: 0 | E60: 95 | F60: 0 | G60: 0
B61: Mobilização | C61: unid | D61: 1 | F61: 0 | G61: 0
B62: Manutenção | C62: mês | D62: 1 | E62: 800 | F62: 800 | G62: 6.0606061
B63: Operador de Equipamento | C63: mês | D63: 1 | E63: 0 | F63: 0 | G63: 0
B64: Diesel | C64: L | D64: 1188 | E64: 5.75 | F64: 4968 | G64: 37.636364
B65: CUSTO TOTAL DE LOCAÇÃO DE EQUIPAMENTOS | F65: 24768 | G65: 187.63636
B67: ROLO LISO
B68: LOCAÇÃO | C68: H X Comb. | D68: 96 | E68: Efetivo | F68: 132
B69: ROLO LISO | D69: QTD. | E69: LOCAÇÃO | F69: TOTAL | G69: CUSTO HORÁRIO
B70: Locação Mensal | C70: mês | D70: 1 | E70: 19000 | F70: 19000 | G70: 143.93939
B71: Hora extra mensal | C71: hh | D71: 0 | E71: 95 | F71: 0 | G71: 0
B72: Mobilização | C72: unid | D72: 1 | F72: 0 | G72: 0
B73: Manutenção | C73: mês | D73: 1 | E73: 800 | F73: 800 | G73: 6.0606061
B74: Operador de Equipamento | C74: mês | D74: 1 | E74: 0 | F74: 0 | G74: 0
B75: Diesel | C75: L | D75: 1188 | E75: 5.75 | F75: 4968 | G75: 37.636364
B76: CUSTO TOTAL DE LOCAÇÃO DE EQUIPAMENTOS | F76: 24768 | G76: 187.63636
B77: ESCAVADEIRA HIDRÁULICA 21 ton com rompedor
B78: LOCAÇÃO | C78: H X Comb. | D78: 96 | E78: Efetivo | F78: 132
B79: ESCAVADEIRA HIDRÁULICA 22TON | D79: QTD. | E79: LOCAÇÃO | F79: TOTAL | G79: CUSTO HORÁRIO
B80: Locação Mensal | C80: mês | D80: 1 | E80: 50160 | F80: 50160 | G80: 380
B81: Manutenção | C81: mês | D81: 1 | E81: 800 | F81: 800 | G81: 6.0606061
B82: Operador de Equipamento | C82: mês | D82: 1 | E82: 10920.188 | F82: 10920.188 | G82: 82.7287
B83: Diesel | C83: L | D83: 1188 | E83: 5.75 | F83: 4968 | G83: 37.636364
B84: CUSTO TOTAL DE LOCAÇÃO DE EQUIPAMENTOS | F84: 66848.188 | G84: 506.42567
B86: ROLO DE PNEUS
B87: LOCAÇÃO | C87: H X Comb. | D87: 96 | E87: Efetivo | F87: 132
B88: ROLO DE PNEUS | D88: QTD. | E88: LOCAÇÃO | F88: TOTAL | G88: CUSTO HORÁRIO
B89: Locação Mensal | C89: mês | D89: 1 | E89: 15000 | F89: 15000 | G89: 113.63636
B90: Hora extra mensal | C90: hh | D90: 0 | E90: 75 | F90: 0 | G90: 0
B91: Manutenção | C91: mês | D91: 1 | E91: 800 | F91: 800 | G91: 6.0606061
B92: Operador de Equipamento | C92: mês | D92: 1 | E92: 0 | F92: 0 | G92: 0
B93: Diesel | C93: L | D93: 1188 | E93: 5.75 | F93: 4968 | G93: 37.636364
B94: CUSTO TOTAL DE LOCAÇÃO DE EQUIPAMENTOS | F94: 20768 | G94: 157.33333
B96: TRATOR AGRÍCOLA COM GRADE DE DISCOS
B97: LOCAÇÃO | C97: H X Comb. | D97: 96 | E97: Efetivo | F97: 132
B98: TRATOR AGRÍCOLA COM GRADE DE DISCOS | D98: QTD. | E98: LOCAÇÃO | F98: TOTAL | G98: CUSTO HORÁRIO
B99: Locação Mensal | C99: mês | D99: 1 | E99: 19000 | F99: 19000 | G99: 143.93939
B100: Hora extra mensal | C100: hh | D100: 0 | E100: 95 | F100: 0 | G100: 0
B101: Mobilização | C101: unid | D101: 1 | F101: 0 | G101: 0
B102: Manutenção | C102: mês | D102: 1 | E102: 800 | F102: 800 | G102: 6.0606061
B103: Operador de Equipamento | C103: mês | D103: 1 | E103: 0 | F103: 0 | G103: 0
B104: Diesel | C104: L | D104: 1848 | E104: 5.75 | F104: 7728 | G104: 58.545455
B105: CUSTO TOTAL DE LOCAÇÃO DE EQUIPAMENTOS | F105: 27528 | G105: 208.54545
B107: CAMINHÃO PIPA
B108: LOCAÇÃO | C108: H X Comb. | D108: 96 | E108: Efetivo | F108: 132
B109: CAMINHÃO PIPA 20.000L | D109: QTD. | E109: LOCAÇÃO | F109: TOTAL | G109: CUSTO HORÁRIO
B110: Locação Mensal | C110: mês | D110: 1 | E110: 15000 | F110: 15000 | G110: 113.63636
B111: Hora extra mensal | C111: hh | E111: 75 | F111: 0 | G111: 0
B112: Mobilização | C112: unid | F112: 0 | G112: 0
B113: Manutenção | C113: mês | E113: 800 | F113: 0 | G113: 0
B114: Operador de Equipamento | C114: mês | D114: 1 | E114: 8164.3033 | F114: 8164.3033 | G114: 61.850782
B115: Diesel | C115: L | D115: 264 | E115: 5.75 | F115: 1104 | G115: 8.3636364
...

Sheet BDI
C3: COMPOSIÇÃO DA TAXA DE BDI
C4: BONIFICAÇÃO DE DESPESAS INDIRETAS
B6: SIGLA | C6: DESCRIÇÃO | D6: PARCELA
B8: AC | C8: Administração Central | D8: 0.035
B9: CF | C9: Custo Financeiro - (PAGAMENTO EM 30 DIAS) | D9: 0.0225
B10: S/G | C10: Seguros / Garantia - (ITEM NÃO CONSIDERADO EM NOSSA PROPOSTA) | D10: 0
B11: MI | C11: Margem de Incerteza | D11: 0.01
B12: T | C12: Tributos | D12: =SUM(D13:D15) -> 0.0765
C13: ISS | D13: 0.04
C14: PIS | D14: 0.0065
C15: COFINS | D15: 0.03
B16: MBC | C16: Margem Bruta de Contribuição | D16: =D17+D18+D19 -> 0.067
C17: Lucro Líquido | D17: 0.05
C18: CSLL | D18: =D17*0.09 -> 0.0045
C19: IRRF | D19: =D17*0.25 -> 0.0125
B21: TAXA DE BDI | D21: =(((1+$D$8+$D$9+$D$10+$D$11))/(1-($D$12+$D$16)))-1 -> 0.24635143
B23: FÓRMULA ADOTADA
B25: BDI = | C25: ((1+AC + CF + S + G + MI) / 1 - (T+MBC) ) - 1 ) x 100
C10716: a | D10716: bc | E10716: d | F10716: g

Sheet BDI-ADM LOCAL
C3: COMPOSIÇÃO DA TAXA DE BDI
C4: BONIFICAÇÃO DE DESPESAS INDIRETAS
B6: SIGLA | C6: DESCRIÇÃO | D6: PARCELA
B8: AC | C8: Administração Central | D8: 0.035
B9: CF | C9: Custo Financeiro - (PAGAMENTO EM 30 DIAS) | D9: 0.0225
B10: S/G | C10: Seguros / Garantia - (ITEM NÃO CONSIDERADO EM NOSSA PROPOSTA) | D10: 0
B11: MI | C11: Margem de Incerteza | D11: 0.01
B12: T | C12: Tributos | D12: =SUM(D13:D15) -> 0.0765
C13: ISS | D13: 0.04
C14: PIS | D14: 0.0065
C15: COFINS | D15: 0.03
B16: MBC | C16: Margem Bruta de Contribuição | D16: =D17+D18+D19 -> 0.059362
C17: Lucro Líquido | D17: 0.0443
C18: CSLL | D18: =D17*0.09 -> 0.003987
C19: IRRF | D19: =D17*0.25 -> 0.011075
B21: TAXA DE BDI | D21: =(((1+$D$8+$D$9+$D$10+$D$11))/(1-($D$12+$D$16)))-1 -> 0.2353351
B23: FÓRMULA ADOTADA
B25: BDI = | C25: ((1+AC + CF + S + G + MI) / 1 - (T+MBC) ) - 1 ) x 100
C10716: a | D10716: bc | E10716: d | F10716: g

Sheet ES
B6: Composição de Encargos Sociais e Obrigações Trabalhistas
B7: DESCRIÇÃO | C7: MENSALISTA | D7: MENSALISTA
B8: GRUPO A
B9: Previdência Social | C9: 0.2 | D9: 0.2
B10: Sesi / Sesc | C10: 0.015 | D10: 0.015
B11: Senai/Senac | C11: 0.01 | D11: 0.01
B12: Incra | C12: 0.002 | D12: 0.002
B13: Salário Educação | C13: 0.025 | D13: 0.025
B14: Seguro Acidente do Trabalho | C14: 0.03 | D14: 0.03
B15: FGTS | C15: 0.08 | D15: 0.08
B16: Sebrae | C16: 0.006 | D16: 0.006
B17: SECONCI | C17: 0.01 | D17: 0.01
B18: TOTAL | C18: =SUM(C9:C17) -> 0.378 | D18: =SUM(D9:D17) -> 0.378
B19: GRUPO B
B20: Repouso Semanal Remunerado | C20: Não incide | D20: Não incide
B21: Férias Gozadas | C21: 0.0802 | D21: 0.0802
B22: Feriados/Dias Santos | C22: Não incide | D22: Não incide
B23: Auxílio - Enfermidade | C23: 0.0067 | D23: 0.0067
B24: Décimo Terceiro Salário | C24: 0.0833 | D24: 0.0833
B25: Licença Paternidade | C25: 0.0006 | D25: 0.0006
B26: Faltas Justificadas | C26: 0.0056 | D26: 0.0056
B27: Dias de Chuvas | C27: Não incide | D27: Não incide
B28: Auxílio Acidente de Trabalho | C28: 0.0008 | D28: 0.0008
B29: Salário Maternidade | C29: 0.0003 | D29: 0.0003
B30: TOTAL | C30: =SUM(C20:C29) -> 0.1775 | D30: =SUM(D20:D29) -> 0.1775
B31: GRUPO C
B32: Aviso Prévio Indenizado | C32: 0.0441 | D32: 0.0441
B33: Aviso Prévio Trabalhado | C33: 0.001 | D33: 0.001
B34: Férias Indenizadas | C34: 0.0248 | D34: 0.0248
B35: Depósito Rescisão Sem Justa Causa | C35: 0.0267 | D35: 0.0267
B36: Indenização Adicional | C36: 0.0037 | D36: 0.0037
B37: TOTAL | C37: =SUM(C32:C36) -> 0.1003 | D37: =SUM(D32:D36) -> 0.1003
B38: GRUPO D
B39: Reincidência de Grupo A sobre Grupo B | C39: 0.067095 | D39: =D30*D18 -> 0.067095
B40: Reincidência de Grupo A sobre Aviso Prévio Trabalhado e Reincidência do FGTS sobre Aviso Prévio Indenizado | C40: 0.003906 | D40: =D18*D33+D15*D32 -> 0.003906
B41: TOTAL | C41: =SUM(C39:C40) -> 0.071001 | D41: =SUM(D39:D40) -> 0.071001
B42: TOTAL(A+B+C+D) | C42: =C41+C37+C30+C18 -> 0.726801 | D42: =D41+D37+D30+D18 -> 0.726801
